Workbook
Name \p: #REF!
Name _0: #REF!
Name _101664: #REF!
Name _101665: #REF!
Name _101745: #REF!
Name _101746: #REF!
Name _102751: #REF!
Name _102752: #REF!
Name _102848: #REF!
Name _102849: #REF!
Name _107282: #REF!
Name _107283: #REF!
Name _107478: #REF!
Name _107479: #REF!
Name _107656: #REF!
Name _107657: #REF!
Name _108949: #REF!
Name _108950: #REF!
Name _109421: #REF!
Name _109422: #REF!
Name _109822: #REF!
Name _109823: #REF!
Name _110840: #REF!
Name _110841: #REF!
Name _111116: #REF!
Name _111117: #REF!
Name _113441: #REF!
Name _113442: #REF!
Name _114894: #REF!
Name _114895: #REF!
Name _15298: #REF!
Name _15299: #REF!
Name _17308: #REF!
Name _17309: #REF!
Name _17618: #REF!
Name _17619: #REF!
Name _19044: #REF!
Name _19045: #REF!
Name _1980: #REF!
Name _1981: #REF!
Name _23100: #REF!
Name _23101: #REF!
Name _2321: #REF!
Name _24408: #REF!
Name _24409: #REF!
Name _26594: #REF!
Name _26595: #REF!
Name _27257: #REF!
Name _27258: #REF!
Name _29061: #REF!
Name _29062: #REF!
Name _29329: #REF!
Name _29330: #REF!
Name _29483: #REF!
Name _29484: #REF!
Name _29732: #REF!
Name _29733: #REF!
Name _29773: #REF!
Name _29774: #REF!
Name _29929: #REF!

Sheet Cover Page
B3: RSM333 Group18 Excel Worksheet
B5: Company: Metro Inc.
B7: Team Members: Sanyah, Dean, Qi, Sydney, Hanum Zahrani, Hanxiang

Sheet Industry Data
A1: Metro Inc. | B1: Industry Data
A3: Company Name | B3: Ticker | C3: Market Capitalization Latest ($USD mm) | D3: LTM Net Debt ($USD mm) | E3: Total Enterprise Value Latest ($USD mm) | F3: LTM Total Revenue ($USD mm) | G3: LTM EBITDA ($USD mm) | H3: LTM Total Debt / EBITDA | I3: LTM Total Debt / Capital %
A4: Loblaw Companies Limited | B4: TSX:L | C4: 53297.3 | D4: 11205.2 | E4: 64623 | F4: 46910.9 | G4: 4136.6 | H4: 2.4 | I4: 0.593
A5: Empire Company Limited | B5: TSX:EMP.A | C5: 8111.7 | D5: 5564.4 | E5: 13612.2 | F5: 23399.1 | G5: 1757.4 | H5: 3.3 | I5: 0.6105
A6: Saputo Inc. | B6: TSX:SAP | C6: 12555.2 | D6: 2247.8 | E6: 14803 | F6: 13942.7 | G6: 1184.8 | H6: 2.1 | I6: 0.3443
A7: Alimentation Couche-Tard Inc. | B7: TSX:ATD | C7: 54911.4 | D7: 13598 | E7: 69024.1 | F7: 72387 | G7: 5469.3 | H7: 2.6 | I7: 0.5033
A8: Colruyt Group N.V. | B8: ENXTBR:COLR | C8: 4691.8 | D8: 739.1 | E8: 5431.3 | F8: 12902.8 | G8: 829.3 | H8: 1.2 | I8: 0.2274
A9: Weis Markets, Inc. | B9: NYSE:WMK | C9: 1544.6 | D9: -2.4 | E9: 1542.2 | F9: 4894.8 | G9: 241.6 | H9: 0.6 | I9: 0.1154
A10: Casey's General Stores, Inc. | B10: NasdaqGS:CASY | C10: 25316.9 | D10: 2430.7 | E10: 27747.6 | F10: 16982.1 | G10: 1389.4 | H10: 2 | I10: 0.429
A11: Shoprite Holdings Ltd | B11: JSE:SHP | C11: 8340.8 | D11: 2501 | E11: 10837.3 | F11: 15633.9 | G11: 1119.6 | H11: 2.4 | I11: 0.6511
A12: Yonghui Superstores Co., Ltd. | B12: SHSE:601933 | C12: 5275.3 | D12: 1448.1 | E12: 6694.3 | F12: 8073.9 | G12: -352.9 | H12: NM | I12: 0.8111
A13: Woolworths Group Limited | B13: ASX:WOW | C13: 31076.8 | D13: 11283.8 | E13: 42447.8 | F13: 49848.9 | G13: 2340.6 | H13: 3.8 | I13: 0.7833
A14: Metro Inc. | B14: TSX:MRU | C14: 14638.2 | D14: 3559.9 | E14: 18211.5 | F14: 16278.9 | G14: 1369.5 | H14: 2.4 | I14: 0.4088

Sheet Competitors WACC
A1: Metro Inc. | B1: Competitor WACC
A3: Company Name | B3: Beta (5Y) | C3: Risk-Free Rate | D3: Market Risk Premium | E3: Cost of Equity | F3: Total Debt (in million) | G3: Interest Expense (in million) | H3: Corporate Tax Rate | I3: After-Tax Cost of Debt | J3: Debt Value / Total Capital (D/V) | K3: Equity Value / Total Capital (E/V) | L3: Minority Interest / Capital (MI/V) | M3: WACC
A4: Loblaw Companies Limited (TSX:L) | B4: 0.42 | C4: 0.0348 | D4: 0.0423 | E4: =C4+B4*D4 -> 0.052566 | F4: 16305 | G4: 763 | H4: 0.2614 | I4: =(G4/F4)*(1-H4) -> 0.034563128 | J4: 0.593 | K4: 0.401 | L4: 0.006 | M4: =J4*I4+K4*E4+L4*E4 -> 0.041890297
A5: Empire Company Limited (TSX:EMP.A) | B5: 0.41 | C5: 0.0348 | D5: 0.0423 | E5: =C5+B5*D5 -> 0.052143 | F5: 7610 | G5: 287.4 | H5: 0.2614 | I5: =(G5/F5)*(1-H5) -> 0.027894039 | J5: 0.575 | K5: 0.415 | L5: 0.01 | M5: =J5*I5+K5*E5+L5*E5 -> 0.038199848
A6: Saputo Inc. (TSX:SAP) | B6: 0.14 | C6: 0.0348 | D6: 0.0423 | E6: =C6+B6*D6 -> 0.040722 | F6: 3509 | G6: 112 | H6: 0.2614 | I6: =(G6/F6)*(1-H6) -> 0.02357458 | J6: 0.344 | K6: 0.656 | L6: 0 | M6: =J6*I6+K6*E6+L6*E6 -> 0.034823287
A7: Alimentation Couche-Tard Inc. (TSX:ATD) | B7: 0.76 | C7: 0.0421 | D7: 0.0446 | E7: =C7+B7*D7 -> 0.075996 | F7: 15722.6 | G7: 655.9 | H7: 0.25 | I7: =(G7/F7)*(1-H7) -> 0.031287764 | J7: 0.503 | K7: 0.492 | L7: 0.005 | M7: =J7*I7+K7*E7+L7*E7 -> 0.053507757
A8: Colruyt Group N.V. (ENXTBR:COLR) | B8: 0.52 | C8: 0.0336 | D8: 0.0501 | E8: =C8+B8*D8 -> 0.059652 | F8: 916.1 | G8: 17.7 | H8: 0.25 | I8: =(G8/F8)*(1-H8) -> 0.014490776 | J8: 0.227 | K8: 0.773 | L8: 0 | M8: =J8*I8+K8*E8+L8*E8 -> 0.049400402
A9: Weis Markets, Inc. (NYSE:WMK) | B9: 0.45 | C9: 0.0421 | D9: 0.0446 | E9: =C9+B9*D9 -> 0.06217 | F9: 175.2 | G9: 0 | H9: 0.25 | I9: =(G9/F9)*(1-H9) -> 0 | J9: 0.115 | K9: 0.885 | L9: 0 | M9: =J9*I9+K9*E9+L9*E9 -> 0.05502045
A10: Casey's General Stores, Inc. (NasdaqGS:CASY) | B10: 0.65 | C10: 0.0421 | D10: 0.0446 | E10: =C10+B10*D10 -> 0.07109 | F10: 2895.7 | G10: 116.9 | H10: 0.25 | I10: =(G10/F10)*(1-H10) -> 0.030277653 | J10: 0.429 | K10: 0.571 | L10: 0 | M10: =J10*I10+K10*E10+L10*E10 -> 0.053581503
A11: Shoprite Holdings Ltd (JSE:SHP) | B11: 0.44 | C11: 0.0872 | D11: 0.0813 | E11: =C11+B11*D11 -> 0.122972 | F11: 57139 | G11: 4394 | H11: 0.27 | I11: =(G11/F11)*(1-H11) -> 0.056137139 | J11: 0.651 | K11: 0.35 | L11: -0.001 | M11: =J11*I11+K11*E11+L11*E11 -> 0.079462506
A12: Yonghui Superstores Co., Ltd. (SHSE:601933) | B12: 0.42 | C12: 0.0182 | D12: 0.0514 | E12: =C12+B12*D12 -> 0.039788 | F12: 14989.9 | G12: 731.1 | H12: 0.25 | I12: =(G12/F12)*(1-H12) -> 0.03657963 | J12: 0.811 | K12: 0.2 | L12: -0.011 | M12: =J12*I12+K12*E12+L12*E12 -> 0.037186012
A13: Woolworths Group Limited (ASX:WOW) | B13: 0.38 | C13: 0.0496 | D13: 0.0423 | E13: =C13+B13*D13 -> 0.065674 | F13: 17198 | G13: 842 | H13: 0.3 | I13: =(G13/F13)*(1-H13) -> 0.034271427 | J13: 0.783 | K13: 0.211 | L13: 0.006 | M13: =J13*I13+K13*E13+L13*E13 -> 0.041085785
A14: Average | B14: =AVERAGE(B4:B13) -> 0.459 | E14: =AVERAGE(E4:E13) -> 0.0642773 | I14: =AVERAGE(I4:I13) -> 0.028907614 | M14: =AVERAGE(M4:M13) -> 0.048415785
A16: Average WACC of ten peers businesses in Food Retail industry is approxiamately 4.842%.
A18: *Alimentation Couche-Tard Inc. (TSX:ATD), Weis Markets, Inc. (NYSE:WMK), Casey's General Stores, Inc. (NasdaqGS:CASY): three US companies with monetary unit of USD, and applying the US risk-free rate and corporate tax rate.
A19: *Colruyt Group N.V. (ENXTBR:COLR): a Belgian company with monetary unit of EUR, and applying the Belgium risk-free rate and corporate tax rate.
A20: *Shoprite Holdings Ltd (JSE:SHP): a South African company with monetary unit of ZAR, and applying the South Africa risk-free rate and corporate tax rate.
A21: *Yonghui Superstores Co., Ltd. (SHSE:601933): a Chinese company with monetary unit of CNY, and applying the China risk-free rate and corporate tax rate.
A22: *Woolworths Group Limited (ASX:WOW): an Australian company with monetary unit of AUD, and applying the Australia risk-free rate and corporate tax rate.

Sheet Debt & Dividend
A2: FQ1 2026 (Dec-20-2025) Detailed Debt Schedule As Reported Details
A3: Description | B3: Type | C3: Principal Due (CAD mm) | D3: Coupon/Base Rate | E3: Floating Rate | F3: Maturity date | G3: Maturity Year
A4: Series G Notes | B4: Bonds and Notes | C4: 450 | D4: 0.0339 | E4: NA | F4: Dec-06-2027 | G4: 2027
A5: Series L Notes | B5: Bonds and Notes | C5: 500 | D5: 0.03998 | E5: NA | F5: Nov-27-2029 | G5: 2029
A7: Summary Metrics
A8: Total Long Term Debt(2026-2029) | B8: =SUM(Table6[Principal Due (CAD mm)]) -> 950
A9: Weighted Avg Coupon Rate | B9: =SUMPRODUCT(Table6[Principal Due (CAD mm)],Table6[Coupon/Base Rate])/SUM(Table6[Principal Due (CAD mm)]) -> 0.0371
A10: Weighted Avg Maturity(year) | B10: =SUMPRODUCT(Table6[Principal Due (CAD mm)],Table6[Maturity Year])/SUM(Table6[Principal Due (CAD mm)]) -> 2028.0526
A11: Debt-to-Capital Ratio | B11: ='Raw - Capital Structure Summary'!G18 -> 0.40880572
A13: Dividend Policy (2021 - 2025)
A15: Year | B15: EPS($) | C15: DPS($) | D15: Payout Ratio | E15: Repurchase of Common Stock($mm) | F15: Common Dividends Paid
A16: 2021 | B16: 3.34281 | C16: 1 | D16: 0.291737 | E16: -456.3 | F16: -240.1
A17: 2022 | B17: 3.526886 | C17: 1.1 | D17: 0.30481 | E17: -470 | F17: -257.9
A18: 2023 | B18: 4.364731 | C18: 1.21 | D18: 0.270989 | E18: -593.6 | F18: -275
A19: 2024 | B19: 4.126166 | C19: 1.34 | D19: 0.317183 | E19: -485.7 | F19: -294.6
A20: 2025 | B20: 4.645957 | C20: 1.48 | D20: 0.311504 | E20: -801.3 | F20: -316.8

Sheet Capital Structure (WACC)
A1: Metro Inc. | B1: Capital Sturcture & WACC
A3: Capital Sturcture Inputs | B3: 12 months Dec-20-2025
A4: Items | B4: Value (CAD mm) | D4: Sources
A5: Total Debt | B5: 4867.2 | D5: (Capital IQ)
A6: Total Equity | B6: 7020.4 | D6: (Capital IQ)
A7: Total Minority Interest | B7: 18.3 | D7: (Capital IQ)
A8: Total Capital | B8: 11905.9 | D8: (Capital IQ)
A10: Capital Structure Weights
A11: Metrics | B11: Value
A12: Debt / Capital (D/V) | B12: =B5/B8 -> 0.40880572
A13: Equity / Capital (E/V) | B13: =B6/B8 -> 0.58965723
A14: Minority Interest / Capital (MI/V) | B14: =B7/B8 -> 0.0015370531
A16: Cost of Equity (CAPM)
A17: Component | B17: Value | D17: Sources
A18: Beta (5Y) | B18: 0.38 | D18: (Capital IQ)
A19: Risk-Free Rate | B19: 0.0348 | D19: (Government of Canada 10-Year Benchmark Bond Yield, Bank of Canada, as of March 11, 2026) | E19: https://www.bankofcanada.ca/rates/interest-rates/canadian-bonds/
A20: Market Risk Premium | B20: 0.0423 | D20: (Professor Aswath Damodaran's Website, Canada Equity Risk Premium (January 2026)) | E20: https://pages.stern.nyu.edu/~adamodar/New_Home_Page/datafile/ctryprem.html
A21: Cost of Equity | B21: =B19+B18*B20 -> 0.050874
A23: Cost of Debt
A24: Component | B24: Value | D24: Sources
A25: Total Debt (CAD mm) | B25: =B5 -> 4867.2 | D25: (Capital IQ)
A26: Interest Expense (CAD mm) | B26: 172.2 | D26: (Capital IQ)
A27: Corporate Tax Rate | B27: 0.2614 | D27: (Professor Aswath Damodaran's Website) | E27: https://pages.stern.nyu.edu/~adamodar/New_Home_Page/datafile/ctryprem.html
A28: Pre-Tax Cost of Debt | B28: =B26/B25 -> 0.035379684
A29: After-Tax Cost of Debt | B29: =B28*(1-B27) -> 0.026131435
A31: WACC
A32: Metrics | B32: Value | D32: Notes
A33: Cost of Equity (CAPM) | B33: =B21 -> 0.050874 | D33: Capital IQ includes minority interest in Metro’s total capital, so we keep it in the capital structure weights. As minority interest is an equity-like non-controlling ownership claim and its size is immaterial, we use the cost of equity as its required rate of return.
A34: After-Tax Cost of Debt | B34: =B29 -> 0.026131435
A35: Weight of Equity | B35: =B13 -> 0.58965723
A36: Weight of Debt | B36: =B12 -> 0.40880572
A37: Weight of Minority Interest | B37: =B14 -> 0.0015370531
A38: Final WACC | B38: =B33*B35+B34*B36+B37*B33 -> 0.040759098

Sheet WACC Explanation 
A1: Explanation of WACC Calculation:
B4: Capital Structure
B5: Using Capital IQ data for the 12 months ending December 20, 2025, Metro’s capital structure is (in CAD mm):
B6: *Total Debt = 4867.2
B7: *Total Equity = 7020.4
B8: *Total Minority Interest = $18.3
B9: *Total Capital = 11905.9
B11: This gives the following three capital weights:
B12: Debt / Capital = 40.88%
B13: Equity / Capital = 58.97%
B14: Minority Interest / Capital = 0.15%
B16: Cost of Equity
B17: Metro's cost of equity is estimated using the CAPM:
... B44: *WACC = (E / V) * Re + (D / V) * Rd(1 - T) + (MI / V) * Rmi = 0.5897 * 5.087% + 0.4088 * 2.613% + 0.0015 * 5.087% = 4.076%

Sheet Comparable Analysis
B2: Metro Inc.
B3: Comparable Company Analysis
B4: (in $M)
D6: Comparable Company Analysis ($M) | N6: Multiples | R6: Key Stats
D7: Company | E7: Ticker | F7: Market Cap | G7: Shares Outstanding | H7: Share Price | I7: Enterprise Value | J7: Revenue | K7: Net Income | L7: EBITDA | N7: EV/Revenue | O7: EV/EBITDA | P7: P/E | R7: Cash & Short Term Investments | S7: 17.9
D8: Loblaws Companies Limited | E8: TSX:L | F8: 75280.4 | G8: 1169.3 | H8: =F8/G8 -> 64.380741 | I8: 90708.4 | J8: 63903 | K8: 2667 | L8: 5635 | N8: =I8/J8 -> 1.4194701 | O8: =I8/L8 -> 16.09732 | P8: =F8/K8 -> 28.226622 | R8: minority interest | S8: 18.3
D9: Empire Company Limited | E9: TSX:EMP.A | F9: 11466.9 | G9: 226.7 | H9: =F9/G9 -> 50.581826 | I9: 19189.9 | J9: 31858 | K9: 159 | L9: 2373 | N9: =I9/J9 -> 0.60235734 | O9: =I9/L9 -> 8.0867678 | P9: =F9/K9 -> 72.118868 | R9: pref. equity | S9: 0
D10: Metro Inc. | E10: TSX:MRU | F10: 20499.1 | G10: 211.7 | H10: =F10/G10 -> 96.830893 | I10: 25366.7 | J10: 22175.4 | K10: 983.7 | L10: 1865.6 | N10: =I10/J10 -> 1.1439117 | O10: =I10/L10 -> 13.597073 | P10: =F10/K10 -> 20.838772 | R10: debt | S10: 4867.2
D12: Minimum | N12: =MIN(N8:N10) -> 0.60235734 | O12: =MIN(O8:O10) -> 8.0867678 | P12: =MIN(P8:P10) -> 20.838772
D13: 25th Percentile | N13: =_xlfn.PERCENTILE.INC(N8:N9,0.25) -> 0.80663554 | O13: =_xlfn.PERCENTILE.INC(O8:O9,0.25) -> 10.089406 | P13: =_xlfn.PERCENTILE.INC(P8:P9,0.25) -> 39.199683
D14: Median | N14: =MEDIAN(N8:N9) -> 1.0109137 | O14: =MEDIAN(O8:O9) -> 12.092044 | P14: =MEDIAN(P8:P9) -> 50.172745
D15: 75th Percentile | N15: =_xlfn.PERCENTILE.INC(N8:N9,0.75) -> 1.2151919 | O15: =_xlfn.PERCENTILE.INC(O8:O9,0.75) -> 14.094682 | P15: =_xlfn.PERCENTILE.INC(P8:P9,0.75) -> 61.145806
D16: Maximum | N16: =MAX(N8:N9) -> 1.4194701 | O16: =MAX(O8:O9) -> 16.09732 | P16: =MAX(P8:P9) -> 72.118868
D19: Implied Valuation
D20: Minimum | N20: =N12*$J$10 -> 13357.515 | O20: =O12*$L$10 -> 15086.674 | P20: =P12*$K$10 -> 20499.1
D21: 25th Percentile | N21: =N13*$J$10 -> 17887.466 | O21: =O13*$L$10 -> 18822.796 | P21: =P13*$K$10 -> 38560.728
D22: Median | N22: =N14*$J$10 -> 22417.416 | O22: =O14*$L$10 -> 22558.917 | P22: =P14*$K$10 -> 49354.929
D23: 75th Percentile | N23: =N15*$J$10 -> 26947.367 | O23: =O15*$L$10 -> 26295.039 | P23: =P15*$K$10 -> 60149.13
D24: Maximum | N24: =N16*$J$10 -> 31477.318 | O24: =O16*$L$10 -> 30031.161 | P24: =P16*$K$10 -> 70943.33
D26: Equity Value
D27: Minimum | N27: =N20+$S$7-$S$8-$S$9-$S$10 -> 8489.9149 | O27: =O20+$S$7-$S$8-$S$9-$S$10 -> 10219.074 | P27: =P20 -> 20499.1
D28: 25th Percentile | N28: =N21+$S$7-$S$8-$S$9-$S$10 -> 13019.866 | O28: =O21+$S$7-$S$8-$S$9-$S$10 -> 13955.196 | P28: =P21 -> 38560.728
D29: Median | N29: =N22+$S$7-$S$8-$S$9-$S$10 -> 17549.816 | O29: =O22+$S$7-$S$8-$S$9-$S$10 -> 17691.317 | P29: =P22 -> 49354.929
D30: 75th Percentile | N30: =N23+$S$7-$S$8-$S$9-$S$10 -> 22079.767 | O30: =O23+$S$7-$S$8-$S$9-$S$10 -> 21427.439 | P30: =P23 -> 60149.13
D31: Maximum | N31: =N24+$S$7-$S$8-$S$9-$S$10 -> 26609.718 | O31: =O24+$S$7-$S$8-$S$9-$S$10 -> 25163.561 | P31: =P24 -> 70943.33
D33: Share Price
D34: Minimum | N34: =MAX((N27/$G$10),0) -> 40.103518 | O34: =MAX((O27/$G$10),0) -> 48.271488 | P34: =MAX((P27/$G$10),0) -> 96.830893
D35: 25th Percentile | N35: =MAX((N28/$G$10),0) -> 61.501491 | O35: =MAX((O28/$G$10),0) -> 65.919677 | P35: =MAX((P28/$G$10),0) -> 182.14798
D36: Median | N36: =MAX((N29/$G$10),0) -> 82.899464 | O36: =MAX((O29/$G$10),0) -> 83.567867 | P36: =MAX((P29/$G$10),0) -> 233.13618
D37: 75th Percentile | N37: =MAX((N30/$G$10),0) -> 104.29744 | O37: =MAX((O30/$G$10),0) -> 101.21606 | P37: =MAX((P30/$G$10),0) -> 284.12437
D38: Maximum | N38: =MAX((N31/$G$10),0) -> 125.69541 | O38: =MAX((O31/$G$10),0) -> 118.86425 | P38: =MAX((P31/$G$10),0) -> 335.11257

Sheet DCF Model 
A1: Metro Inc. DCF Valuation
A2: Share Price as of December 31, 2025 | B2: 98.79
A3: Shares outstanding | B3: 211.7
A5: Model Assumptions
A6: Assumption | B6: Value
A7: Years in Forecast | B7: 5 Years
A8: WACC | B8: ='Capital Structure (WACC)'!B38 -> 0.040759098
A9: Terminal Growth Rate | B9: 0.0145
A10: Terminal EV / EBITDA Multiple | B10: 12.37x
A12: Forecast Financials (DCF Table)
A13: Fiscal Years Ending September 30th | B13: F2021A | C13: F2022A | D13: F2023A | E13: F2024A | F13: F2025A | G13: F2026E | H13: F2027E | I13: F2028E | J13: F2029E | K13: F2030E | L13: F2031E
A14: Period | B14: -4 | C14: -3 | D14: -2 | E14: -1 | F14: 0 | G14: 1 | H14: 2 | I14: 3 | J14: 4 | K14: 5 | L14: 6
A15: Revenue | B15: ='Raw - Income Statement'!B20 -> 18283 | C15: ='Raw - Income Statement'!C20 -> 18888.9 | D15: ='Raw - Income Statement'!D20 -> 20724.6 | E15: ='Raw - Income Statement'!E20 -> 21219.9 | F15: ='Raw - Income Statement'!F20 -> 22006.7 | G15: =Table128[[#This Row],[F2025A]]*(1+G16) -> 22677.657 | H15: =Table128[[#This Row],[F2026E]]*(1+H16) -> 23369.326 | I15: =Table128[[#This Row],[F2027E]]*(1+I16) -> 24082.09 | J15: =Table128[[#This Row],[F2028E]]*(1+J16) -> 24816.594 | K15: =Table128[[#This Row],[F2029E]]*(1+K16) -> 25573.5 | L15: =Table128[[#This Row],[F2030E]]*(1+L16) -> 26353.492
A16: % Growth | B16: n.a | C16: =(C15-B15)/B15 -> 0.033140075 | D16: =(D15-C15)/C15 -> 0.09718406 | E16: =(E15-D15)/D15 -> 0.023899134 | F16: =(F15-E15)/E15 -> 0.037078403 | G16: =(Table128[[#This Row],[F2025A]]+Table128[[#This Row],[F2024A]])/2 -> 0.030488769 | H16: 0.0305 | I16: 0.0305 | J16: 0.0305 | K16: 0.0305 | L16: 0.0305
A17: Less: COGS and other expenses | B17: ='Raw - Income Statement'!B35 -> 16562.2 | C17: ='Raw - Income Statement'!C35 -> 17069.9 | D17: ='Raw - Income Statement'!D35 -> 18756 | E17: ='Raw - Income Statement'!E35 -> 19233.5 | F17: ='Raw - Income Statement'!F35 -> 19941 | G17: =Table128[[#This Row],[F2025A]]*(1+G18) -> 20587.498 | H17: =Table128[[#This Row],[F2026E]]*(1+H18) -> 21241.586 | I17: =Table128[[#This Row],[F2027E]]*(1+I18) -> 21946.528 | J17: =Table128[[#This Row],[F2028E]]*(1+J18) -> 22662.892 | K17: =Table128[[#This Row],[F2029E]]*(1+K18) -> 23400.8 | L17: =Table128[[#This Row],[F2030E]]*(1+L18) -> 24166.875
A18: % Growth | B18: n.a | C18: =(C17-B17)/B17 -> 0.03065414 | D18: =(D17-C17)/C17 -> 0.098776208 | E18: =(E17-D17)/D17 -> 0.02545852 | F18: =(F17-E17)/E17 -> 0.036784777 | G18: =0.5*Table128[[#This Row],[F2025A]]+0.25*Table128[[#This Row],[F2024A]]+0.25*Table128[[#This Row],[F2022A]] -> 0.032420553 | H18: =0.5*Table128[[#This Row],[F2026E]]+0.25*Table128[[#This Row],[F2025A]]+0.25*Table128[[#This Row],[F2024A]] -> 0.031771101 | I18: =0.5*Table128[[#This Row],[F2027E]]+0.25*Table128[[#This Row],[F2026E]]+0.25*Table128[[#This Row],[F2025A]] -> 0.033186883 | J18: =0.5*Table128[[#This Row],[F2028E]]+0.25*Table128[[#This Row],[F2027E]]+0.25*Table128[[#This Row],[F2026E]] -> 0.032641355 | K18: =0.5*Table128[[#This Row],[F2029E]]+0.25*Table128[[#This Row],[F2028E]]+0.25*Table128[[#This Row],[F2027E]] -> 0.032560173 | L18: =0.5*Table128[[#This Row],[F2030E]]+0.25*Table128[[#This Row],[F2029E]]+0.25*Table128[[#This Row],[F2028E]] -> 0.032737146
A19: EBITDA | B19: =B15-B17 -> 1720.8 | C19: =C15-C17 -> 1819 | D19: =D15-D17 -> 1968.6 | E19: =E15-E17 -> 1986.4 | F19: =F15-F17 -> 2065.7 | G19: =G15-G17 -> 2090.1589 | H19: =H15-H17 -> 2127.74 | I19: =I15-I17 -> 2135.5624 | ... L19: =L15-L17 -> 2186.6165
A20: % Margin | B20: =B19/B15 -> 0.094120221 | C20: =C19/C15 -> 0.096299943 | D20: =D19/D15 -> 0.094988564 | E20: =E19/E15 -> 0.093610243 | F20: =F19/F15 -> 0.093866868 | G20: =G19/G15 -> 0.092168204 | H20: =H19/H15 -> 0.091048412 | I20: =I19/I15 -> 0.088678449 | ... L20: =L19/L15 -> 0.082972554
A21: Less: D&A | B21: ='Raw - Income Statement'!B27 -> 478.3 | C21: ='Raw - Income Statement'!C27 -> 503.3 | D21: ='Raw - Income Statement'!D27 -> 525.2 | E21: ='Raw - Income Statement'!E27 -> 570.4 | F21: ='Raw - Income Statement'!F27 -> 594.4 | G21: =0.026*G15 -> 589.61909 | H21: =0.026*H15 -> 607.60247 | I21: =0.026*I15 -> 626.13434 | J21: =0.026*J15 -> 645.23144 | K21: =0.026*K15 -> 664.911 | L21: =0.026*L15 -> 685.19079
A22: EBIT | B22: =B19-B21 -> 1242.5 | C22: =C19-C21 -> 1315.7 | D22: =D19-D21 -> 1443.4 | E22: =E19-E21 -> 1416 | F22: =F19-F21 -> 1471.3 | G22: =G19-G21 -> 1500.5398 | H22: =H19-H21 -> 1520.1375 | I22: =I19-I21 -> 1509.4281 | ... L22: =L19-L21 -> 1501.4257
A23: % Margin | B23: =B22/B15 -> 0.067959306 | C23: =C22/C15 -> 0.069654665 | D23: =D22/D15 -> 0.0696467 | E23: =E22/E15 -> 0.066729815 | F23: =F22/F15 -> 0.066856912 | G23: =G22/G15 -> 0.066168204 | H23: =H22/H15 -> 0.065048412 | I23: =I22/I15 -> 0.062678449 | ... L23: =L22/L15 -> 0.056972554
A24: Tax Rate | B24: ='Raw - Income Statement'!B89 -> 0.263228 | C24: ='Raw - Income Statement'!C89 -> 0.263609 | D24: ='Raw - Income Statement'!D89 -> 0.229232 | E24: ='Raw - Income Statement'!E89 -> 0.254699 | F24: ='Raw - Income Statement'!F89 -> 0.227768 | G24: =0.2*Table128[[#This Row],[F2025A]]+0.2*Table128[[#This Row],[F2024A]]+0.2*Table128[[#This Row],[F2023A]]+0.2*Table128[[#This Row],[F2022A]]+0.2*Table128[[#This Row],[F2021A]] -> 0.2477072 | H24: =0.2*Table128[[#This Row],[F2026E]]+0.2*Table128[[#This Row],[F2025A]]+0.2*Table128[[#This Row],[F2024A]]+0.2*Table128[[#This Row],[F2023A]]+0.2*Table128[[#This Row],[F2022A]] -> 0.24460304 | I24: =0.2*Table128[[#This Row],[F2027E]]+0.2*Table128[[#This Row],[F2026E]]+0.2*Table128[[#This Row],[F2025A]]+0.2*Table128[[#This Row],[F2024A]]+0.2*Table128[[#This Row],[F2023A]] -> 0.24080185 | J24: =0.2*Table128[[#This Row],[F2028E]]+0.2*Table128[[#This Row],[F2027E]]+0.2*Table128[[#This Row],[F2026E]]+0.2*Table128[[#This Row],[F2025A]]+0.2*Table128[[#This Row],[F2024A]] -> 0.24311582 | K24: =0.2*Table128[[#This Row],[F2029E]]+0.2*Table128[[#This Row],[F2028E]]+0.2*Table128[[#This Row],[F2027E]]+0.2*Table128[[#This Row],[F2026E]]+0.2*Table128[[#This Row],[F2025A]] -> 0.24079918 | L24: =0.2*Table128[[#This Row],[F2030E]]+0.2*Table128[[#This Row],[F2029E]]+0.2*Table128[[#This Row],[F2028E]]+0.2*Table128[[#This Row],[F2027E]]+0.2*Table128[[#This Row],[F2026E]] -> 0.24340542
A25: Less: Taxes | B25: =B24*B22 -> 327.06079 | C25: =C24*C22 -> 346.83036 | D25: =D24*D22 -> 330.87347 | E25: =E24*E22 -> 360.65378 | F25: =F24*F22 -> 335.11506 | G25: =G24*G22 -> 371.69452 | H25: =H24*H22 -> 371.83026 | I25: =I24*I22 -> 363.47307 | ... L25: =L24*L22 -> 365.45516
A26: EBIAT | B26: =B22-B25 -> 915.43921 | C26: =C22-C25 -> 968.86964 | D26: =D22-D25 -> 1112.5265 | E26: =E22-E25 -> 1055.3462 | F26: =F22-F25 -> 1136.1849 | G26: =G22-G25 -> 1128.8453 | H26: =H22-H25 -> 1148.3073 | I26: =I22-I25 -> 1145.955 | ... L26: =L22-L25 -> 1135.9706
A27: Plus: D&A | B27: =B21 -> 478.3 | C27: =C21 -> 503.3 | D27: =D21 -> 525.2 | E27: =E21 -> 570.4 | F27: =F21 -> 594.4 | G27: =G21 -> 589.61909 | H27: =H21 -> 607.60247 | I27: =I21 -> 626.13434 | ... L27: =L21 -> 685.19079
A28: Operating cash flow | B28: =B26+B27 -> 1393.7392 | C28: =C26+C27 -> 1472.1696 | D28: =D26+D27 -> 1637.7265 | E28: =E26+E27 -> 1625.7462 | F28: =F26+F27 -> 1730.5849 | G28: =G26+G27 -> 1718.4644 | H28: =H26+H27 -> 1755.9097 | I28: =I26+I27 -> 1772.0893 | ... L28: =L26+L27 -> 1821.1614
A29: Net Working Capital | B29: ='Raw - Balance Sheet'!B72 -> 268.6 | C29: ='Raw - Balance Sheet'!C72 -> 230.8 | D29: ='Raw - Balance Sheet'!D72 -> 442.8 | E29: ='Raw - Balance Sheet'!E72 -> 188.4 | F29: ='Raw - Balance Sheet'!F72 -> 607.2 | G29: =G30*G15 -> 484.32426 | H29: =H30*H15 -> 462.61823 | I29: =I30*I15 -> 533.05952 | J29: =J30*J15 -> 529.97732 | K29: =K30*K15 -> 541.15181 | L29: =L30*L15 -> 565.36251
A30: NWC as a % of revenue | B30: =B29/B15 -> 0.014691243 | C30: =C29/C15 -> 0.012218816 | D30: =D29/D15 -> 0.021365913 | E30: =E29/E15 -> 0.0088784584 | F30: =F29/F15 -> 0.027591597 | G30: =0.5*Table128[[#This Row],[F2025A]]+0.25*Table128[[#This Row],[F2024A]]+0.25*Table128[[#This Row],[F2023A]] -> 0.021356891 | H30: =0.5*Table128[[#This Row],[F2026E]]+0.25*Table128[[#This Row],[F2025A]]+0.25*Table128[[#This Row],[F2024A]] -> 0.01979596 | I30: =0.5*Table128[[#This Row],[F2027E]]+0.25*Table128[[#This Row],[F2026E]]+0.25*Table128[[#This Row],[F2025A]] -> 0.022135102 | J30: =0.5*Table128[[#This Row],[F2028E]]+0.25*Table128[[#This Row],[F2027E]]+0.25*Table128[[#This Row],[F2026E]] -> 0.021355764 | K30: =0.5*Table128[[#This Row],[F2029E]]+0.25*Table128[[#This Row],[F2028E]]+0.25*Table128[[#This Row],[F2027E]] -> 0.021160647 | L30: =0.5*Table128[[#This Row],[F2030E]]+0.25*Table128[[#This Row],[F2029E]]+0.25*Table128[[#This Row],[F2028E]] -> 0.02145304
A31: Add/Less: Changes in Working Capital | B31: n.a | C31: =C29-B29 -> -37.8 | D31: =D29-C29 -> 212 | E31: =E29-D29 -> -254.4 | F31: =F29-E29 -> 418.8 | G31: =G29-F29 -> -122.87574 | H31: =H29-G29 -> -21.706034 | I31: =I29-H29 -> 70.441293 | J31: =J29-I29 -> -3.0822046 | ... L31: =L29-K29 -> 24.210701
A32: Capex as a % of Revenue | B32: =B33/B15 -> 0.025663184 | C32: =C33/C15 -> 0.026327632 | D32: =D33/D15 -> 0.028019841 | E32: =E33/E15 -> 0.022733378 | F32: =F33/F15 -> 0.019912118 | G32: =AVERAGE(Table128[[#This Row],[F2021A]:[F2025A]]) -> 0.02453123 | H32: =AVERAGE(Table128[[#This Row],[F2021A]:[F2025A]]) -> 0.02453123 | I32: =AVERAGE(Table128[[#This Row],[F2021A]:[F2025A]]) -> 0.02453123 | J32: =AVERAGE(Table128[[#This Row],[F2021A]:[F2025A]]) -> 0.02453123 | K32: =AVERAGE(Table128[[#This Row],[F2021A]:[F2025A]]) -> 0.02453123 | L32: =AVERAGE(Table128[[#This Row],[F2021A]:[F2025A]]) -> 0.02453123
A33: Less: Capex | B33: =ABS('Raw - Cash Flow'!B31) -> 469.2 | C33: =ABS('Raw - Cash Flow'!C31) -> 497.3 | D33: =ABS('Raw - Cash Flow'!D31) -> 580.7 | E33: =ABS('Raw - Cash Flow'!E31) -> 482.4 | F33: =ABS('Raw - Cash Flow'!F31) -> 438.2 | G33: =0.0245*G15 -> 555.6026 | H33: =0.025*H15 -> 584.23314 | I33: =0.025*I15 -> 602.05225 | J33: =0.025*J15 -> 620.41485 | K33: =0.025*K15 -> 639.3375 | L33: =0.025*L15 -> 658.83729
A34: Unlevered Free Cash Flows (FCFF) | B34: n.a | C34: =C28-C33-C31 -> 1012.6696 | D34: =D28-D33-D31 -> 845.02653 | E34: =E28-E33-E31 -> 1397.7462 | F34: =F28-F33-F31 -> 873.58494 | G34: =G28-G33-G31 -> 1285.7375 | H34: =H28-H33-H31 -> 1193.3826 | I34: =I28-I33-I31 -> 1099.5958 | J34: =J28-J33-J31 -> 1169.6361 | K34: =K28-K33-K31 -> 1159.1138 | L34: =L28-L31-L33 -> 1138.1134
A35: PV of Free Cash Flows | B35: n.a | C35: =C34*((1+$B$8)^3) -> 1141.6118 | D35: =D34*((1+$B$8)^2) -> 915.31542 | E35: =E34*((1+$B$8)^1) -> 1454.7171 | F35: =F34/((1+$B$8)^F14) -> 873.58494 | G35: =G34/((1+$B$8)^G14) -> 1235.3844 | H35: =H34/((1+$B$8)^H14) -> 1101.7404 | I35: =I34/((1+$B$8)^I14) -> 975.39926 | J35: =J34/((1+$B$8)^J14) -> 996.89612 | K35: =K34/((1+$B$8)^K14) -> 949.23772 | L35: =L34/((1+$B$8)^L14) -> 895.53843
A37: Terminal Value | D37: Multiple | E37: GRIP | F37: gordon
A38: Terminal EBITDA / FCF | D38: =L19 -> 2186.6165 | E38: =L34 -> 1138.1134
A39: Terminal Multiple / Growth Rate | D39: 12.37 | E39: =B9 -> 0.0145
A40: Terminal Value | D40: =D38*D39 -> 27048.446 | E40: =(E38*(1+E39))/(B8-B9) -> 43970.132
A41: PV of Terminal Value | D41: =D40/((1+B8)^L14) -> 21283.401 | E41: =E40/((1+B8)^L14) -> 34598.437
A42: PV FCF | D42: =SUM(G35:L35) -> 6154.1963 | E42: =Table139[[#This Row],[Column4]] -> 6154.1963
A43: Enterprise Value | D43: =D41+D42 -> 27437.597 | E43: =E41+E42 -> 40752.633
A44: (-) Debt | D44: ='Capital Structure (WACC)'!B25 -> 4867.2 | E44: =Table139[[#This Row],[Column4]] -> 4867.2
A45: (+) Cash | D45: ='Raw - Balance Sheet'!G18 -> 17.9 | E45: =Table139[[#This Row],[Column4]] -> 17.9
A46: Implied Equity Value | D46: =D43+D44+D45 -> 32322.697 | E46: =E43+E44+E45 -> 45637.733
A48: Implied Share Price | D48: Multiple | E48: GRIP
A49: Impiled Equity Value | B49: =D46 -> 32322.697 | D49: =D46/B3 -> 152.68161 | E49: =E46/B3 -> 215.57739
A50: Implied Upside/Downside | D50: =(D49-B2)/B2 -> 0.54551688 | E50: =(E49-B2)/B2 -> 1.1821782
A53: Sensitivity Analysis
B54: WACC
B55: =D49 -> 152.68161 | C55: 0.031 | D55: 0.036 | E55: 0.040759098 | F55: 0.046 | G55: 0.051
B56: 6400 | C56: 159.68936 | D56: 156.64572 | E56: 153.84271 | F56: 150.85796 | G56: 148.10635
A57: PV FCF | B57: 6600 | C57: 160.6341 | D57: 157.59046 | E57: 154.78744 | F57: 151.80269 | G57: 149.05108
B58: 6154.2 | C58: 158.52829 | D58: 155.48465 | E58: 152.68163 | F58: 149.69688 | G58: 146.94527
B59: 7000 | C59: 162.52356 | D59: 159.47992 | E59: 156.67691 | F59: 153.69216 | G59: 150.94055
B60: 7200 | C60: 163.4683 | D60: 160.42466 | E60: 157.62164 | F60: 154.63689 | G60: 151.88528
B62: Terminal EDITDA
B63: =D49 -> 152.68161 | C63: =D63*0.9 -> 1771.146 | D63: =E63*0.9 -> 1967.94 | E63: 2186.6 | F63: =E63*1.1 -> 2405.26 | G63: =F63*1.1 -> 2645.786
B64: =B65*0.9 -> 10.0197 | C64: 118.1069 | D64: 125.43589 | E64: 133.57922 | F64: 141.72255 | G64: 150.68021
B65: =B66*0.9 -> 11.133 | C65: 125.43589 | D65: 133.57922 | E65: 142.62736 | F65: 151.6755 | G65: 161.62846
A66: Terminal Multiple | B66: 12.37 | C66: 133.57922 | D66: 142.62736 | E66: 152.68085 | F66: 162.73434 | G66: 173.79318
B67: =B66*1.1 -> 13.607 | C67: 141.72255 | D67: 151.6755 | E67: 162.73434 | F67: 173.79318 | G67: 185.95791
B68: =B67*1.1 -> 14.9677 | C68: 150.68021 | D68: 161.62846 | E68: 173.79318 | F68: 185.95791 | G68: 199.3391

Sheet Raw - Cash Flow
A5: Metro Inc. (TSX:MRU) > Financials > Cash Flow
A7: In Millions of the reported currency, except per share items. | B7: Template: | C7: Standard | E7: Restatement: | F7: Latest Filings
B8: Period Type: | C8: Annual | E8: Order: | F8: Latest on Right
B9: Currency: | C9: Reported Currency | E9: Conversion: | F9: Historical
B10: Units: | C10: S&P Capital IQ (Default) | E10: Decimals: | F10: Capital IQ (Default)
B11: Source: | C11: Capital IQ & Proprietary Data
A14: Cash Flow
A15: For the Fiscal Period Ending | B15: 12 months Sep-25-2021 | C15: 12 months Sep-24-2022 | D15: 12 months Sep-30-2023 | E15: Restated 12 months Sep-28-2024 | F15: 12 months Sep-27-2025 | G15: LTM 12 months Dec-20-2025
A16: Currency | B16: CAD | C16: CAD | D16: CAD | E16: CAD | F16: CAD | G16: CAD
A18: Net Income | B18: 823 | C18: 846.1 | D18: 1014.8 | E18: 928.8 | F18: 1017 | G18: 983.7
A19: Depreciation & Amort. | B19: 400.1 | C19: 421.4 | D19: 439 | E19: 477.7 | F19: 500.7 | G19: 510.7
A20: Amort. of Goodwill and Intangibles | B20: 58.8 | C20: 58.3 | D20: 59.3 | E20: 60.8 | F20: 59 | G20: 59
A21: Depreciation & Amort., Total | B21: 458.9 | C21: 479.7 | D21: 498.3 | E21: 538.5 | F21: 559.7 | G21: 569.7
A23: Other Amortization | B23: 21.1 | C23: 25.3 | D23: 28.3 | E23: 33.3 | F23: 36.2 | G23: 36.2
A24: (Gain) Loss From Sale Of Assets | B24: -7.4 | C24: -25.3 | D24: -4.2 | E24: -6.8 | F24: -0.1 | G24: 2.8
A25: Asset Writedown & Restructuring Costs | B25: - | C25: 70.1 | D25: - | E25: 20.8 | F25: - | G25: -
A26: Stock-Based Compensation | B26: 10.6 | C26: 8.6 | D26: 12 | E26: 13.1 | F26: 13.8 | G26: 14.3
A27: Other Operating Activities | B27: 114.9 | C27: 172.1 | D27: 139.8 | E27: 206.6 | F27: 225 | G27: 260.4
A28: Change in Other Net Operating Assets | B28: 162.2 | C28: -115.2 | D28: -125.5 | E28: -57.3 | F28: -126.7 | G28: -190.3
A29: Cash from Ops. | B29: 1583.3 | C29: 1461.4 | D29: 1563.5 | E29: 1677 | F29: 1724.9 | G29: 1676.8
A31: Capital Expenditure | B31: -469.2 | C31: -497.3 | D31: -580.7 | E31: -482.4 | F31: -438.2 | G31: -412
A32: Sale of Property, Plant, and Equipment | B32: 22.4 | C32: 21.6 | D32: 1.2 | E32: 0.8 | F32: 5.6 | G32: 0.8
A33: Cash Acquisitions | B33: -1.1 | C33: -0.2 | D33: -1.4 | E33: - | F33: -1 | G33: -0.7
A34: Divestitures | B34: - | C34: - | D34: - | E34: - | F34: - | G34: -
A35: Sale (Purchase) of Real Estate properties | B35: -50.8 | C35: -25.5 | D35: -16.5 | E35: -16.6 | F35: -14.3 | G35: -14.3
A36: Sale (Purchase) of Intangible assets | B36: -79.3 | C36: -98.2 | D36: -82.7 | E36: -80.7 | F36: -58.1 | G36: -56.9
A37: Invest. in Marketable & Equity Securt. | B37: - | C37: - | D37: - | E37: 13.3 | F37: - | G37: -
A38: Net (Inc.) Dec. in Loans Originated/Sold | B38: - | C38: - | D38: - | E38: - | F38: - | G38: -
A39: Other Investing Activities | B39: 106.4 | C39: 121.8 | D39: 107.6 | E39: 109.2 | F39: 97.4 | G39: 93.2
A40: Cash from Investing | B40: -471.6 | C40: -477.8 | D40: -572.5 | E40: -456.4 | F40: -408.6 | G40: -389.9
A42: Short Term Debt Issued | B42: - | C42: - | D42: - | E42: - | F42: - | G42: -
A43: Long-Term Debt Issued | B43: 21.9 | C43: 330.5 | D43: 500.9 | E43: 327.5 | F43: 707.9 | G43: -
A44: Total Debt Issued | B44: 21.9 | C44: 330.5 | D44: 500.9 | E44: 327.5 | F44: 707.9 | G44: 446.6
A45: Short Term Debt Repaid | B45: -0.3 | C45: - | D45: - | E45: - | F45: - | G45: -
A46: Long-Term Debt Repaid | B46: -284.9 | C46: -884.8 | D46: -457.3 | E46: -604.2 | F46: -713.1 | G46: -
A47: Total Debt Repaid | B47: -285.2 | C47: -884.8 | D47: -457.3 | E47: -604.2 | F47: -713.1 | G47: -379
A49: Issuance of Common Stock | B49: 12.6 | C49: 21 | D49: 7.8 | E49: 18.9 | F49: 24.1 | G49: 18.8
A50: Repurchase of Common Stock | B50: -456.3 | C50: -470 | D50: -593.6 | E50: -485.7 | F50: -801.3 | G50: -851.5
A52: Common Dividends Paid | B52: -240.1 | C52: -257.9 | D52: -275 | E52: -294.6 | F52: -316.8 | G52: -321.7
A53: Total Dividends Paid | B53: -240.1 | C53: -257.9 | D53: -275 | E53: -294.6 | F53: -316.8 | G53: -321.7
A55: Special Dividend Paid | B55: - | C55: - | D55: - | E55: - | F55: - | G55: -
A56: Other Financing Activities | B56: -160.3 | C56: -154.8 | D56: -157.7 | E56: -182.6 | F56: -179.2 | G56: -182.2
A57: Cash from Financing | B57: -1107.4 | C57: -1416 | D57: -974.9 | E57: -1220.7 | F57: -1278.4 | G57: -1269
A59: Net Change in Cash | B59: 4.3 | C59: -432.4 | D59: 16.1 | E59: -0.1 | F59: 37.9 | G59: 17.9
A61: Supplemental Items
A62: Cash Interest Paid | B62: 157.7 | C62: 151.2 | D62: 157.9 | E62: 182.6 | F62: 179.2 | G62: 182.2
A63: Cash Taxes Paid | B63: 328.1 | C63: 257.6 | D63: 309.4 | E63: 276.1 | F63: 288 | G63: 277.2
A64: Levered Free Cash Flow | B64: 697.1625 | C64: 559.6375 | D64: 485.5 | E64: 777.9625 | F64: 840.5625 | G64: 840.7875
A65: Unlevered Free Cash Flow | B65: 784.9625 | C65: 641.8125 | D65: 578.725 | E65: 881.5 | F65: 942.5625 | G65: 946.9125
A66: Change in Net Working Capital | B66: -66.8 | C66: 100.9 | D66: 199 | E66: 28.8 | F66: 93.2 | G66: 123
A67: Net Debt Issued | B67: -263.3 | C67: -554.3 | D67: 43.6 | E67: -276.7 | F67: -5.2 | G67: 67.6
A68: Filing Date | B68: 44915 | C68: 45280 | D68: 45640 | E68: 46004 | F68: 46004 | G68: 46049
A69: Restatement Type | B69: NC | C69: NC | D69: NC | E69: RS | F69: O | G69: O
A70: Calculation Type | B70: REP | C70: REP | D70: REP | E70: REP | F70: REP | G70: LTM

Sheet Raw - Income Statement
A5: Metro Inc. (TSX:MRU) > Financials > Income Statement
A7: In Millions of the reported currency, except per share items. | B7: Template: | C7: Standard | E7: Restatement: | F7: Latest Filings
B8: Period Type: | C8: Annual | E8: Order: | F8: Latest on Right
B9: Currency: | C9: Reported Currency | E9: Conversion: | F9: Historical
B10: Units: | C10: S&P Capital IQ (Default) | E10: Decimals: | F10: Capital IQ (Default)
B11: Source: | C11: Capital IQ & Proprietary Data
A14: Income Statement
A15: For the Fiscal Period Ending | B15: Reclassified 12 months Sep-25-2021 | C15: 12 months Sep-24-2022 | D15: 12 months Sep-30-2023 | E15: 12 months Sep-28-2024 | F15: 12 months Sep-27-2025 | G15: LTM 12 months Dec-20-2025
A16: Currency | B16: CAD | C16: CAD | D16: CAD | E16: CAD | F16: CAD | G16: CAD
A18: Revenue | B18: 18283 | C18: 18888.9 | D18: 20724.6 | E18: 21219.9 | F18: 22006.7 | G18: 22175.4
A19: Other Revenue | B19: - | C19: - | D19: - | E19: - | F19: - | G19: -
A20: Total Revenue | B20: 18283 | C20: 18888.9 | D20: 20724.6 | E20: 21219.9 | F20: 22006.7 | G20: 22175.4
A22: Cost Of Goods Sold | B22: 14628.2 | C22: 15105.6 | D22: 16642.4 | E22: 17040.6 | F22: 17660.9 | G22: 17796.5
A23: Gross Profit | B23: 3654.8 | C23: 3783.3 | D23: 4082.2 | E23: 4179.3 | F23: 4345.8 | G23: 4378.9
A25: Selling General & Admin Exp. | B25: 1934 | C25: 1964.3 | D25: 2113.6 | E25: 2192.9 | F25: 2280.1 | G25: 2309.2
A26: R & D Exp. | B26: 0 | C26: 0 | D26: 0 | E26: - | F26: - | G26: -
A27: Depreciation & Amort. | B27: 478.3 | C27: 503.3 | D27: 525.2 | E27: 570.4 | F27: 594.4 | G27: 604.4
A28: Other Operating Expense/(Income) | B28: 0 | C28: 0 | D28: 0 | E28: - | F28: - | G28: -
A30: Other Operating Exp., Total | B30: 2412.3 | C30: 2467.6 | D30: 2638.8 | E30: 2763.3 | F30: 2874.5 | G30: 2913.6
A33: Operating Income | B33: 1242.5 | C33: 1315.7 | D33: 1443.4 | E33: 1416 | F33: 1471.3 | G33: 1465.3
A35: Total Costs (excluding D&A) | B35: =B30-B27+B22 -> 16562.2 | C35: =C30-C27+C22 -> 17069.9 | D35: =D30-D27+D22 -> 18756 | E35: =E30-E27+E22 -> 19233.5 | F35: =F30-F27+F22 -> 19941 | G35: =G30-G27+G22 -> 20105.7
A37: EBITDA | B37: =B20-B35 -> 1720.8 | C37: =C20-C35 -> 1819 | D37: =D20-D35 -> 1968.6 | E37: =E20-E35 -> 1986.4 | F37: =F20-F35 -> 2065.7 | G37: =G20-G35 -> 2069.7
A39: Interest Expense | B39: -143.2 | C39: -134.2 | D39: -151.4 | E39: -167.9 | F39: -165.6 | G39: -172.2
A40: Interest and Invest. Income | B40: 14.3 | C40: 17.2 | D40: 25.9 | E40: 16.2 | F40: 14.7 | G40: 14.7
A41: Net Interest Exp. | B41: -128.9 | C41: -117 | D41: -125.5 | E41: -151.7 | F41: -150.9 | G41: -157.5
A43: Other Non-Operating Inc. (Exp.) | B43: -0.3 | C43: -0.3 | D43: -0.3 | E43: -0.2 | F43: -0.3 | G43: -0.3
A44: EBT Excl. Unusual Items | B44: 1113.3 | C44: 1198.4 | D44: 1317.6 | E44: 1264.1 | F44: 1320.1 | G44: 1307.5
A46: Impairment of Goodwill | B46: - | C46: - | D46: - | E46: - | F46: - | G46: -
A47: Gain (Loss) On Sale Of Assets | B47: 7.4 | C47: 25.3 | D47: 4.2 | E47: 6.8 | F47: 0.1 | G47: -2.8
A48: Asset Writedown | B48: - | C48: -70.1 | D48: - | E48: -20.8 | F48: - | G48: -
A49: Other Unusual Items | B49: - | C49: - | D49: - | E49: - | F49: - | G49: -
A50: EBT Incl. Unusual Items | B50: 1120.7 | C50: 1153.6 | D50: 1321.8 | E50: 1250.1 | F50: 1320.2 | G50: 1304.7
A52: Income Tax Expense | B52: 295 | C52: 304.1 | D52: 303 | E52: 318.4 | F52: 300.7 | G52: 318.4
A53: Earnings from Cont. Ops. | B53: 825.7 | C53: 849.5 | D53: 1018.8 | E53: 931.7 | F53: 1019.5 | G53: 986.3
A55: Earnings of Discontinued Ops. | B55: - | C55: - | D55: - | E55: - | F55: - | G55: -
A56: Extraord. Item & Account. Change | B56: - | C56: - | D56: - | E56: - | F56: - | G56: -
A57: Net Income to Company | B57: 825.7 | C57: 849.5 | D57: 1018.8 | E57: 931.7 | F57: 1019.5 | G57: 986.3
A59: Minority Int. in Earnings | B59: -2.7 | C59: -3.4 | D59: -4 | E59: -2.9 | F59: -2.5 | G59: -2.6
A60: Net Income | B60: 823 | C60: 846.1 | D60: 1014.8 | E60: 928.8 | F60: 1017 | G60: 983.7
A62: Pref. Dividends and Other Adj. | B62: - | C62: - | D62: - | E62: - | F62: - | G62: -
A64: NI to Common Incl Extra Items | B64: 823 | C64: 846.1 | D64: 1014.8 | E64: 928.8 | F64: 1017 | G64: 983.7
A65: NI to Common Excl. Extra Items | B65: 823 | C65: 846.1 | D65: 1014.8 | E65: 928.8 | F65: 1017 | G65: 983.7
A67: Per Share Items
A68: Basic EPS | B68: 3.34281 | C68: 3.526886 | D68: 4.364731 | E68: 4.126166 | F68: 4.645957 | G68: 4.535792
A69: Basic EPS Excl. Extra Items | B69: 3.34281 | C69: 3.526886 | D69: 4.364731 | E69: 4.126166 | F69: 4.645957 | G69: 4.535792
A70: Weighted Avg. Basic Shares Out. | B70: 246.2 | C70: 239.9 | D70: 232.5 | E70: 225.1 | F70: 218.9 | G70: 216.875
A72: Diluted EPS | B72: 3.33 | C72: 3.51 | D72: 4.35 | E72: 4.11 | F72: 4.63 | G72: 4.52146
A73: Diluted EPS Excl. Extra Items | B73: 3.33 | C73: 3.51 | D73: 4.35 | E73: 4.11 | F73: 4.63 | G73: 4.52146
A74: Weighted Avg. Diluted Shares Out. | B74: 247.3 | C74: 240.8 | D74: 233.3 | E74: 225.8 | F74: 219.7 | G74: 217.675
A76: Normalized Basic EPS | B76: 2.815241 | C76: 3.107961 | D76: 3.524731 | E76: 3.496945 | F76: 3.757708 | G76: 3.756023
A77: Normalized Diluted EPS | B77: 2.802719 | C77: 3.096345 | D77: 3.512644 | E77: 3.486104 | F77: 3.744025 | G77: 3.742218
A79: Dividends per Share | B79: 1 | C79: 1.1 | D79: 1.21 | E79: 1.34 | F79: 1.48 | G79: 1.48
A80: Payout Ratio % | B80: 0.291737 | C80: 0.30481 | D80: 0.270989 | E80: 0.317183 | F80: 0.311504 | G80: 0.32703
A82: Shares per Depository Receipt | B82: 0.2 | C82: 0.2 | D82: 0.2 | E82: 0.2 | F82: 0.2 | G82: 0.2
A84: Supplemental Items
A85: EBITDA | B85: 1542.8 | C85: 1634.9 | D85: 1780.7 | E85: 1790.2 | F85: 1861.6 | G85: 1865.6
A86: EBITA | B86: 1301.3 | C86: 1374 | D86: 1502.7 | E86: 1476.8 | F86: 1530.3 | G86: 1524.3
A87: EBIT | B87: 1242.5 | C87: 1315.7 | D87: 1443.4 | E87: 1416 | F87: 1471.3 | G87: 1465.3
A88: EBITDAR | B88: 1670.6 | C88: 1763.2 | D88: 1913.5 | E88: 1925.3 | F88: 2015.1 | G88: NA
A89: Effective Tax Rate % | B89: 0.263228 | C89: 0.263609 | D89: 0.229232 | E89: 0.254699 | F89: 0.227768 | G89: 0.24404
A90: Total Current Taxes | B90: 254.9 | C90: 299.1 | D90: 249.5 | E90: 293.8 | F90: 283.8 | G90: 283.8
A91: Total Deferred Taxes | B91: 40.1 | C91: 5 | D91: 53.5 | E91: 24.6 | F91: 16.9 | G91: 16.9
A93: Normalized Net Income | B93: 693.1125 | C93: 745.6 | D93: 819.5 | E93: 787.1625 | F93: 822.5625 | G93: 814.5875
A94: Interest on Long Term Debt | B94: 155.4 | C94: 145.8 | D94: 160.2 | E94: 170.6 | F94: 175.7 | G94: NA
A95: Non-Cash Pension Expense | B95: 7.9 | C95: 3.4 | D95: -0.8 | E95: -4.8 | F95: -6.3 | G95: -
A96: Filing Date | B96: 44915 | C96: 45280 | D96: 45640 | E96: 46004 | F96: 46004 | G96: 46049
A97: Restatement Type | B97: RC | C97: NC | D97: NC | E97: NC | F97: O | G97: O
A98: Calculation Type | B98: REP | C98: REP | D98: REP | E98: REP | F98: REP | G98: LTM
A100: Supplemental Operating Expense Items
A101: Net Rental Exp. | B101: 127.8 | C101: 128.3 | D101: 132.8 | E101: 135.1 | F101: 153.5 | G101: NA
A102: Imputed Oper. Lease Interest Exp. | B102: 31.599317 | C102: 31.660334 | D102: 37.960614 | E102: 41.96206 | F102: 45.62634 | G102: -
A103: Imputed Oper. Lease Depreciation | B103: 96.200683 | C103: 96.639666 | D103: 94.839386 | E103: 93.13794 | F103: 107.87366 | G103: -
A105: Stock-Based Comp., Unallocated | B105: 11.8 | C105: 12.6 | D105: 13.8 | E105: 18 | F105: 18.1 | G105: 18.6
A106: Stock-Based Comp., Total | B106: 11.8 | C106: 12.6 | D106: 13.8 | E106: 18 | F106: 18.1 | G106: 18.6
A109: Note: For multiple class companies, per share items are primary class equivalent, and for foreign companies listed as primary ADRs, per share items are ADR-equivalent.

Sheet Raw - Balance Sheet
A5: Metro Inc. (TSX:MRU) > Financials > Balance Sheet
A7: In Millions of the reported currency, except per share items. | B7: Template: | C7: Standard | E7: Restatement: | F7: Latest Filings
B8: Period Type: | C8: Annual | E8: Order: | F8: Latest on Right
B9: Currency: | C9: Reported Currency | E9: Conversion: | F9: Historical
B10: Units: | C10: S&P Capital IQ (Default) | E10: Decimals: | F10: Capital IQ (Default)
B11: Source: | C11: Capital IQ & Proprietary Data
A14: Balance Sheet
A15: Balance Sheet as of: | B15: 44464 | C15: 44828 | D15: 45199 | E15: 45563 | F15: 45927 | G15: 46011
A16: Currency | B16: CAD | C16: CAD | D16: CAD | E16: CAD | F16: CAD | G16: CAD
A17: ASSETS
A18: Cash And Equivalents | B18: 445.8 | C18: 13.4 | D18: 29.5 | E18: 29.4 | F18: 67.3 | G18: 17.9
A19: Total Cash & ST Investments | B19: 445.8 | C19: 13.4 | D19: 29.5 | E19: 29.4 | F19: 67.3 | G19: 17.9
A21: Accounts Receivable | B21: 772 | C21: 775.1 | D21: 824.4 | E21: 836.3 | F21: 856 | G21: 959.1
A22: Other Receivables | B22: 33.4 | C22: 9.6 | D22: 32.8 | E22: 17.3 | F22: 43.9 | G22: 50.8
A23: Total Receivables | B23: 805.4 | C23: 784.7 | D23: 857.2 | E23: 853.6 | F23: 899.9 | G23: 1009.9
A25: Inventory | B25: 1169 | C25: 1331.1 | D25: 1451 | E25: 1508.3 | F25: 1604.3 | G25: 1859.2
A26: Prepaid Exp. | B26: 46.6 | C26: 54.1 | D26: 65.9 | E26: 73.2 | F26: 79.4 | G26: 97.5
A27: Other Current Assets | B27: - | C27: - | D27: - | E27: 9.5 | F27: 10.1 | G27: -
A28: Total Current Assets | B28: 2466.8 | C28: 2183.3 | D28: 2403.6 | E28: 2474 | F28: 2661 | G28: 2984.5
A30: Gross Property, Plant & Equipment | B30: 5979.9 | C30: 6470 | D30: 6911.3 | E30: 7336.1 | F30: 7819.1 | G30: -
A31: Accumulated Depreciation | B31: -1785.4 | C31: -2017.2 | D31: -2200.2 | E31: -2430.9 | F31: -2733.5 | G31: -
A32: Net Property, Plant & Equipment | B32: 4194.5 | C32: 4452.8 | D32: 4711.1 | E32: 4905.2 | F32: 5085.6 | G32: 5106
A34: Goodwill | B34: 3301.2 | C34: 3301.2 | D34: 3307.4 | E34: 3314.2 | F34: 3317.1 | G34: 3317.1
A35: Other Intangibles | B35: 2854.7 | C35: 2739 | D35: 2733 | E35: 2698.9 | F35: 2661.2 | G35: 2650.6
A36: Accounts Receivable Long-Term | B36: 549.6 | C36: 478.3 | D36: 426.5 | E36: 404.7 | F36: 376.2 | G36: 357
A37: Deferred Tax Assets, LT | B37: 57.1 | C37: 44.8 | D37: 37.9 | E37: 35.9 | F37: 34.2 | G37: 34.2
A38: Other Long-Term Assets | B38: 168.2 | C38: 201.9 | D38: 245.8 | E38: 307.7 | F38: 404.1 | G38: 402.1
A39: Total Assets | B39: 13592.1 | C39: 13401.3 | D39: 13865.3 | E39: 14140.6 | F39: 14539.4 | G39: 14851.5
A41: LIABILITIES
A42: Accounts Payable | B42: 1546.5 | C42: 1575.8 | D42: 1619.4 | E42: 1645.9 | F42: 1661.8 | G42: 1717.4
A43: Short-term Borrowings | B43: 0.1 | C43: - | D43: - | E43: - | F43: - | G43: -
A44: Curr. Port. of LT Debt | B44: 318.5 | C44: 18.3 | D44: 19.3 | E44: 317.2 | F44: 17.2 | G44: 16.3
A45: Curr. Port. of Leases | B45: 269.7 | C45: 276.3 | D45: 278.4 | E45: 263.6 | F45: 275.9 | G45: 278.5
A46: Curr. Income Taxes Payable | B46: 25.9 | C46: 43.6 | D46: 6.9 | E46: 16.2 | F46: 54.3 | G46: 33.1
A47: Unearned Revenue, Current | B47: 35.9 | C47: 38.5 | D47: 36.8 | E47: 42.7 | F47: 44.6 | G47: 58.8
A48: Other Current Liabilities | B48: 1.6 | C48: - | D48: - | E48: - | F48: - | G48: -
A49: Total Current Liabilities | B49: 2198.2 | C49: 1952.5 | D49: 1960.8 | E49: 2285.6 | F49: 2053.8 | G49: 2104.1
A51: Long-Term Debt | B51: 2318.2 | C51: 2339.9 | D51: 2659.1 | E51: 2358.4 | F51: 2938.1 | G51: 3175.3
A52: Long-Term Leases | B52: 1657.5 | C52: 1502.7 | D52: 1380.3 | E52: 1372.6 | F52: 1370.8 | G52: 1397.1
A53: Unearned Revenue, Non-Current | B53: - | C53: 2.8 | D53: 3 | E53: - | F53: - | G53: -
A54: Pension & Other Post-Retire. Benefits | B54: 61.5 | C54: 30 | D54: 29.4 | E54: 37.5 | F54: 38.3 | G54: 39.2
A55: Def. Tax Liability, Non-Curr. | B55: 927.7 | C55: 942.2 | D55: 1001.6 | E55: 1042.2 | F55: 1088.9 | G55: 1091.9
A56: Other Non-Current Liabilities | B56: 16.2 | C56: 12.8 | D56: 14.8 | E56: 5.4 | F56: 4.4 | G56: 5.2
A57: Total Liabilities | B57: 7179.3 | C57: 6782.9 | D57: 7049 | E57: 7101.7 | F57: 7494.3 | G57: 7812.8
A59: Common Stock | B59: 1674.3 | C59: 1649.3 | D59: 1601.1 | E59: 1575.5 | F59: 1544.7 | G59: 1535.3
A60: Additional Paid In Capital | B60: 24.2 | C60: 23.3 | D60: 23.6 | E60: 25.5 | F60: 26.9 | G60: 29.1
A61: Retained Earnings | B61: 4721.9 | C61: 4947.2 | D61: 5195.6 | E61: 5441.4 | F61: 5481.6 | G61: 5482.4
A62: Treasury Stock | B62: -20.5 | C62: -16.2 | D62: -17.9 | E62: -19.6 | F62: -25.1 | G62: -25.1
A63: Comprehensive Inc. and Other | B63: - | C63: 0.9 | D63: -1.2 | E63: -1.1 | F63: -1.4 | G63: -1.3
A64: Total Common Equity | B64: 6399.9 | C64: 6604.5 | D64: 6801.2 | E64: 7021.7 | F64: 7026.7 | G64: 7020.4
A66: Minority Interest | B66: 12.9 | C66: 13.9 | D66: 15.1 | E66: 17.2 | F66: 18.4 | G66: 18.3
A68: Total Equity | B68: 6412.8 | C68: 6618.4 | D68: 6816.3 | E68: 7038.9 | F68: 7045.1 | G68: 7038.7
A70: Total Liabilities And Equity | B70: 13592.1 | C70: 13401.3 | D70: 13865.3 | E70: 14140.6 | F70: 14539.4 | G70: 14851.5
A72: Net Working Capital | B72: =B28-B49 -> 268.6 | C72: =C28-C49 -> 230.8 | D72: =D28-D49 -> 442.8 | E72: =E28-E49 -> 188.4 | F72: =F28-F49 -> 607.2 | G72: =G28-G49 -> 880.4
A73: Change in NWC | B73: n.a | C73: =C72-B72 -> -37.8 | D73: =D72-C72 -> 212 | E73: =E72-D72 -> -254.4 | F73: =F72-E72 -> 418.8 | G73: =G72-F72 -> 273.2
A75: Supplemental Items
A76: Total Shares Out. on Filing Date | B76: 240.62565 | C76: 235.141 | D76: 227.93989 | E76: 222.11502 | F76: 214.748 | G76: 213.152
A77: Total Shares Out. on Balance Sheet Date | B77: 242.949 | C77: 236.594 | D77: 228.653 | E77: 222.414 | F77: 214.748 | G77: 213.152
A78: Book Value/Share | B78: 26.342565 | C78: 27.914909 | D78: 29.744634 | E78: 31.570404 | F78: 32.720677 | G78: 32.93612
A79: Tangible Book Value | B79: 244 | C79: 564.3 | D79: 760.8 | E79: 1008.6 | F79: 1048.4 | G79: 1052.7
A80: Tangible Book Value/Share | B80: 1.004326 | C80: 2.385098 | D80: 3.327312 | E80: 4.534786 | F80: 4.882001 | G80: 4.938729
A81: Total Debt | B81: 4564 | C81: 4137.2 | D81: 4337.1 | E81: 4311.8 | F81: 4602 | G81: 4867.2
A82: Net Debt | B82: 4118.2 | C82: 4123.8 | D82: 4307.6 | E82: 4282.4 | F82: 4534.7 | G82: 4849.3
A83: Debt Equiv. of Unfunded Proj. Benefit Obligation | B83: -133.6 | C83: -160.4 | D83: -215.3 | E83: -255.3 | F83: -349.7 | G83: NA
A84: Debt Equivalent Oper. Leases | B84: 1022.4 | C84: 1026.4 | D84: 1062.4 | E84: 1080.8 | F84: 1228 | G84: NA
A85: Total Minority Interest | B85: 12.9 | C85: 13.9 | D85: 15.1 | E85: 17.2 | F85: 18.4 | G85: 18.3
A86: Inventory Method | B86: Avg Cost | C86: Avg Cost | D86: Avg Cost | E86: Avg Cost | F86: Avg Cost | G86: NA
A87: Finished Goods Inventory | B87: 1169 | C87: 1331.1 | D87: 1451 | E87: 1508.3 | F87: 1604.3 | G87: NA
A88: Land | B88: 534.7 | C88: 557.9 | D88: 566 | E88: 582.6 | F88: 595.3 | G88: NA
A89: Buildings | B89: 1568.7 | C89: 1759.3 | D89: 1925.1 | E89: 2044.1 | F89: 2077.3 | G89: NA
A90: Machinery | B90: 1852.5 | C90: 2143.7 | D90: 2421.6 | E90: 2647.3 | F90: 2920.6 | G90: NA
A91: Leasehold Improvements | B91: 959.3 | C91: 1014 | D91: 1055.8 | E91: 1108.2 | F91: 1203.3 | G91: -
A92: Full Time Employees | B92: 44097 | C92: 95000 | D92: 97000 | E92: 97870 | F92: 99000 | G92: NA
A93: Filing Date | B93: 44915 | C93: 45280 | D93: 45640 | E93: 46004 | F93: 46004 | G93: 46049
A94: Restatement Type | B94: NC | C94: NC | D94: NC | E94: NC | F94: O | G94: O
A95: Calculation Type | B95: REP | C95: REP | D95: REP | E95: REP | F95: REP | G95: REP
A98: Note: For multiple class companies, total share counts are primary class equivalent, and for foreign companies listed as primary ADRs, total share counts are ADR-equivalent.

Sheet Raw - Key Stats
A5: Metro Inc. (TSX:MRU) > Financials > Key Stats
A7: In Millions of the trading currency, except per share items. | B7: Currency: | C7: Trading Currency | E7: Conversion: | F7: Historical
B8: Order: | C8: Latest on Right | E8: Units: | F8: S&P Capital IQ (Default)
B9: Decimals: | C9: Capital IQ (Default) | E9: Dilution: | F9: Basic
A12: Key Financials¹
A13: For the Fiscal Period Ending | B13: 12 months Sep-24-2022A | C13: 12 months Sep-30-2023A | D13: 12 months Sep-28-2024A | E13: 12 months Sep-27-2025A | F13: LTM² 12 months Dec-20-2025A | G13: 12 months† Sep-30-2026E | H13: 12 months Sep-30-2027E | I13: 12 months Sep-30-2028E
A14: Currency | B14: CAD | C14: CAD | D14: CAD | E14: CAD | F14: CAD | G14: CAD | H14: CAD | I14: CAD
A16: Total Revenue | B16: 18888.9 | C16: 20724.6 | D16: 21219.9 | E16: 22006.7 | F16: 22175.4 | G16: 22731.708 | H16: 23447.982 | I16: 24260.121
A17: Growth Over Prior Year | B17: 0.03314 | C17: 0.097184 | D17: 0.023899 | E17: 0.037078 | F17: 0.038038 | G17: 0.032944889 | H17: 0.031509907 | I17: 0.034635761
A19: Gross Profit | B19: 3783.3 | C19: 4082.2 | D19: 4179.3 | E19: 4345.8 | F19: 4378.9 | G19: - | H19: - | I19: -
A20: Margin % | B20: 0.200292 | C20: 0.196973 | D20: 0.196951 | E20: 0.197476 | F20: 0.197466 | G20: 0.1990647 | H20: 0.1997504 | I20: 0.1997842
A22: EBITDA | B22: 1634.9 | C22: 1780.7 | D22: 1790.2 | E22: 1861.6 | F22: 1865.6 | G22: 2185.9141 | H22: 2291.7266 | I22: 2368.3732
A23: Margin % | B23: 0.086553 | C23: 0.085922 | D23: 0.084364 | E23: 0.084592 | F23: 0.084129 | G23: 0.096161454 | H23: 0.097736624 | I23: 0.097624131
A25: EBIT | B25: 1315.7 | C25: 1443.4 | D25: 1416 | E25: 1471.3 | F25: 1465.3 | G25: 1588.255 | H25: 1669.7336 | I25: 1742.633
A26: Margin % | B26: 0.069654 | C26: 0.069646 | D26: 0.066729 | E26: 0.066856 | F26: 0.066077 | G26: 0.069869585 | H26: 0.071210118 | I26: 0.071831176
A28: Earnings from Cont. Ops. | B28: 849.5 | C28: 1018.8 | D28: 931.7 | E28: 1019.5 | F28: 986.3 | G28: - | H28: - | I28: -
A29: Margin % | B29: 0.044973 | C29: 0.049158 | D29: 0.043906 | E29: 0.046326 | F29: 0.044477 | G29: - | H29: - | I29: -
A31: Net Income | B31: 846.1 | C31: 1014.8 | D31: 928.8 | E31: 1017 | F31: 983.7 | G31: 1087.4207 | H31: 1147.4595 | I31: 1198.9331
A32: Margin % | B32: 0.044793 | C32: 0.048965 | D32: 0.04377 | E32: 0.046213 | F32: 0.044359 | G32: 0.047837173 | H32: 0.048936386 | I32: 0.049419914
A34: Diluted EPS Excl. Extra Items³ | B34: 3.51 | C34: 4.35 | D34: 4.11 | E34: 4.63 | F34: 4.52146 | G34: 5.15478 | H34: 5.60818 | I34: 5.99618
A35: Growth Over Prior Year | B35: 0.054054 | C35: 0.239316 | D35: -0.055173 | E35: 0.12652 | F35: 0.056441 | G35: 0.080666667 | H35: 0.087957197 | I35: 0.069184655
A38: Currency | B38: CAD | C38: CAD | D38: CAD | E38: CAD | F38: CAD | G38: CAD | H38: CAD | I38: CAD
A39: Exchange Rate | B39: 1 | C39: 1 | D39: 1 | E39: 1 | F39: 1 | G39: 1 | H39: 1 | I39: 1
A40: Conversion Method | B40: H | C40: H | D40: H | E40: H | F40: H | G40: S | H40: S | I40: S
A42: ¹All results are taken from the most recently filed statement for each period. When there has been more than one, earlier filings can be viewed on the individual statement pages.
A43: ²Growth rates for the LTM period are calculated against the LTM period ending 12 months before.
A44: ³All forward period figures are consensus mean estimates provided by the brokers and may not be on a comparable basis as financials.
A45: †Growth rates for forward periods are calculated against prior period estimates or actual pro forma results as disclosed on the Estimates Consensus page.
A46: Growth Rates are calculated in originally reported currency only and will not reflect any currency conversion selected above.
A48: Current Capitalization (Millions of CAD)
A49: Currency | B49: CAD
A50: Share Price | B50: 95.12
A51: Shares Out. | B51: 212.67531
A53: Market Capitalization | B53: 20229.676
A54: - Cash & Short Term Investments | B54: 17.9
A55: + Total Debt | B55: 4867.2
A56: + Pref. Equity | B56: -
A57: + Total Minority Interest | B57: 18.3
A58: - Long Term Marketable Securities | B58: -
A59: = Total Enterprise Value (TEV) | B59: 25097.276
A61: Book Value of Common Equity | B61: 7020.4
A62: + Pref. Equity | B62: -
A63: + Total Minority Interest | B63: 18.3
A64: + Total Debt | B64: 4867.2
A65: = Total Capital | B65: 11905.9
A67: **For companies that have multiple share classes that publicly trade, we are incorporating the different prices to calculate our company level market capitalization. Please click on the value to see the detailed calculation. Prices shown on this page are the close price of the company’s primary stock class. Shares shown on this page are total company as-reported share values.
A71: Total Liability includes Total Debt, Minority Interest and Pref. Equity.
A72: Net Liability includes Total Liability, net of Cash and Short Term Investments.
A73: TEV includes Market Cap and Net Liability.
A74: Total Capital includes Common Equity and Total Liability.
A76: Valuation Multiples based on Current Capitalization
A77: For the Fiscal Period Ending | B77: 12 months Sep-27-2025A | C77: LTM 12 months Dec-20-2025A | D77: 12 months Sep-30-2026E | E77: 12 months Sep-30-2027E | F77: 12 months Sep-30-2028E
A78: TEV/Total Revenue | B78: 1.126146 | C78: 1.131762 | D78: 1.1040647 | E78: 1.0703384 | F78: 1.0345074
A80: TEV/EBITDA | B80: 12.202252 | C80: 12.332813 | D80: 11.481364 | E80: 10.951252 | F80: 10.596841
A82: TEV/EBIT | B82: 16.844134 | C82: 17.127738 | D82: 15.801792 | E82: 15.030707 | F82: 14.401928
A84: P/Diluted EPS Before Extra | B84: 20.544276 | C84: 21.037452 | D84: 18.452776 | E84: 16.960939 | F84: 15.863433
A86: P/BV | B86: 2.90703 | C86: 2.888014 | D86: 2.8407895 | E86: 2.6582782 | F86: 2.5113701
A88: Price/Tang BV | B88: 19.483814 | C88: 19.260016 | D88: - | E88: - | F88: -

Sheet Raw - Capital Structure Summary
A5: Metro Inc. (TSX:MRU) > Financials > Capital Structure Summary
A7: In Millions of the reported currency, except ratios and % of Total values. | B7: Restatement: | C7: Latest Filings | E7: Period Type: | F7: Annual
B8: Currency: | C8: Reported Currency | E8: Conversion: | F8: Historical
B9: Units: | C9: S&P Capital IQ (Default) | E9: Decimals: | F9: Capital IQ (Default)
B10: Order: | C10: Latest on Right
A13: Capital Structure Data
A14: For the Fiscal Period Ending | B14: 12 months Sep-28-2024 | D14: 12 months Sep-27-2025 | F14: 3 months Dec-20-2025
A15: Currency | B15: CAD | D15: CAD | F15: CAD
A16: Units | B16: Millions | C16: % of Total | D16: Millions | E16: % of Total | F16: Millions | G16: % of Total
A18: Total Debt | B18: 4311.8 | C18: 0.37987084 | D18: 4602 | E18: 0.39511982 | F18: 4867.2 | G18: 0.40880572
A19: Total Common Equity | B19: 7021.7 | C19: 0.61861383 | D19: 7026.7 | E19: 0.60330039 | F19: 7020.4 | G19: 0.58965723
A20: Total Minority Interest | B20: 17.2 | C20: 0.001515325 | D20: 18.4 | E20: 0.0015797924 | F20: 18.3 | G20: 0.0015370531
A21: Total Capital | B21: 11350.7 | C21: 1 | D21: 11647.1 | E21: 1 | F21: 11905.9 | G21: 1
A25: Debt Summary Data
A26: For the Fiscal Period Ending | B26: 12 months Sep-28-2024 | D26: 12 months Sep-27-2025 | F26: 3 months Dec-20-2025
A27: Currency | B27: CAD | D27: CAD | F27: CAD
A28: Units | B28: Millions | C28: % of Total | D28: Millions | E28: % of Total | F28: Millions | G28: % of Total
A30: Total Revolving Credit | B30: 35.4 | C30: 0.00821 | D30: 118 | E30: 0.025641 | F30: 353.8 | G30: 0.07269
A31: Total Term Loans | B31: 51.5 | C31: 0.011943 | D31: 49.9 | E31: 0.010843 | F31: 37.8 | G31: 0.007766
A32: Total Senior Bonds and Notes | B32: 2598.8 | C32: 0.602718 | D32: 2800 | E32: 0.608431 | F32: 2800 | G32: 0.575279
A33: Total Lease Liabilities | B33: 1636.2 | C33: 0.37947 | D33: 1646.7 | E33: 0.357822 | F33: 1675.6 | G33: 0.344263
A34: Total Principal Due | B34: 4321.9 | C34: 1.002342 | D34: 4614.6 | E34: 1.002737 | F34: 4867.2 | G34: 1
A36: Total Adjustments | B36: -10.1 | C36: -0.002342 | D36: -12.6 | E36: -0.002737 | F36: - | G36: -
A37: Total Debt Outstanding | B37: 4311.8 | C37: 1 | D37: 4602 | E37: 1 | F37: 4867.2 | G37: 1
A39: Available Credit
A40: Undrawn Revolving Credit | B40: - | C40: - | D40: 482 | E40: - | F40: 246.2 | G40: -
A41: Total Undrawn Credit | B41: - | C41: - | D41: 482 | E41: - | F41: 246.2 | G41: -
A43: Additional Totals
A44: Total Cash & ST Investments | B44: 29.4 | C44: - | D44: 67.3 | E44: - | F44: 17.9 | G44: -
A45: Net Debt | B45: 4282.4 | C45: - | D45: 4534.7 | E45: - | F45: 4849.3 | G45: -
A46: Total Senior Debt | B46: 4321.9 | C46: 1.002342 | D46: 4614.6 | E46: 1.002737 | F46: 4867.2 | G46: 1
A47: Curr. Port. of LT Debt/Cap. Leases | B47: 580.8 | C47: 0.1347 | D47: 293.1 | E47: 0.063689 | F47: 294.8 | G47: 0.060568
A48: Long-Term Debt (Incl. Cap. Leases) | B48: 3731 | C48: 0.865299 | D48: 4308.9 | E48: 0.93631 | F48: 4572.4 | G48: 0.939431
A49: Total Bank Debt | B49: 86.9 | C49: 0.020153 | D49: 167.9 | E49: 0.036484 | F49: 391.6 | G49: 0.080456
A50: Total Secured Debt | B50: 1636.2 | C50: 0.37947 | D50: 1646.7 | E50: 0.357822 | F50: 1675.6 | G50: 0.344263
A51: Total Senior Secured Debt | B51: 1636.2 | C51: 0.37947 | D51: 1646.7 | E51: 0.357822 | F51: 1675.6 | G51: 0.344263
A52: Total Unsecured Debt | B52: 2685.7 | C52: 0.622872 | D52: 2967.9 | E52: 0.644915 | F52: 3191.6 | G52: 0.655736
A53: Senior Unsecured Bonds and Notes | B53: 2598.8 | C53: 0.602718 | D53: 2800 | E53: 0.608431 | F53: 2800 | G53: 0.575279
A54: Fixed Rate Debt | B54: 2598.8 | C54: 0.602718 | D54: 2800 | E54: 0.608431 | F54: 2800 | G54: 0.575279
A55: Variable Rate Debt | B55: 86.9 | C55: 0.020153 | D55: 167.9 | E55: 0.036484 | F55: 391.6 | G55: 0.080456
A56: Hedging Activities | B56: 1.3 | C56: 0.000301 | D56: - | E56: - | F56: - | G56: -
A58: Credit Ratios
A59: Net Debt/EBITDA | B59: 2.191046 | C59: - | D59: 2.232742 | E59: - | F59: 2.505839 | G59: -
A60: Total Debt/EBITDA | B60: 2.206088 | C60: - | D60: 2.265878 | E60: - | F60: 2.515089 | G60: -
A61: Total Senior Debt/EBITDA | B61: 2.211256 | C61: - | D61: 2.272082 | E61: - | F61: 2.515089 | G61: -
A62: Total Senior Secured/EBITDA | B62: 0.837145 | C62: - | D62: 0.810782 | E62: - | F62: 0.865854 | G62: -
A63: Net Debt/(EBITDA-CAPEX) | B63: 2.909041 | C63: - | D63: 2.846998 | E63: - | F63: 2.796597 | G63: -
A64: Total Debt/(EBITDA-CAPEX) | B64: 2.929012 | C64: - | D64: 2.889251 | E64: - | F64: 2.80692 | G64: -
A65: Total Senior Debt/(EBITDA-CAPEX) | B65: 2.935873 | C65: - | D65: 2.897162 | E65: - | F65: 2.80692 | G65: -
A66: Total Senior Secured/(EBITDA-CAPEX) | B66: 1.111473 | C66: - | D66: 1.033839 | E66: - | F66: 0.966321 | G66: -
A68: Fixed Payment Schedule
A69: LT Debt (Incl. Cap. Leases) Due +1 | B69: 579.45358 | C69: 0.13438786 | D69: 293.02698 | E69: 0.063673833 | F69: - | G69: -
A70: LT Debt (Incl. Cap. Leases) Due +2 | B70: 303.455 | C70: 0.070377801 | D70: 268.31986 | E70: 0.058305055 | F70: - | G70: -
A71: LT Debt (Incl. Cap. Leases) Due +3 | B71: 233.51282 | C71: 0.054156692 | D71: 680.97217 | E71: 0.14797309 | F71: - | G71: -
A72: LT Debt (Incl. Cap. Leases) Due +4 | B72: 646.63538 | C72: 0.14996878 | D72: 194.83506 | E72: 0.042337041 | F72: - | G72: -
A73: LT Debt (Incl. Cap. Leases) Due +5 | B73: 161.63855 | C73: 0.037487488 | D73: 760.29022 | E73: 0.16520865 | F73: - | G73: -
A74: LT Debt (Incl. Cap. Leases) Due, Next 5 Yrs | B74: 1924.6953 | C74: 0.44637862 | D74: 2197.4443 | E74: 0.47749767 | F74: - | G74: -
A75: LT Debt (Incl. Cap. Leases) Due, After 5 Yrs | B75: 2385.8047 | C75: 0.55331988 | D75: 2404.5557 | E75: 0.52250233 | F75: - | G75: -
A77: Cap. Lease Payment Due +1 | B77: 263.6 | C77: - | D77: 275.9 | E77: - | F77: 278.5 | G77: -
A78: Cap. Lease Payment Due +2 | B78: 265.91503 | C78: - | D78: 264.9343 | E78: - | F78: - | G78: -
A79: Cap. Lease Payment Due +3 | B79: 230.92386 | C79: - | D79: 230.99068 | E79: - | F79: - | G79: -
A80: Cap. Lease Payment Due +4 | B80: 197.45017 | C80: - | D80: 193.73973 | E80: - | F80: - | G80: -
A81: Cap. Lease Payment Due +5 | B81: 160.94152 | C81: - | D81: 144.21686 | E81: - | F81: - | G81: -
A82: Cap. Lease Payment Due, Next 5 Yrs | B82: 1118.8306 | C82: - | D82: 1109.7816 | E82: - | F82: 278.5 | G82: -
A83: Cap. Lease Payment Due, After 5 Yrs | B83: 517.36942 | C83: - | D83: 536.91843 | E83: - | F83: 1397.1 | G83: -
A84: Cap. Lease Payment Due (incl. Interest) +1 | B84: - | C84: - | D84: 335 | E84: - | F84: - | G84: -
A86: Sub-Lease Income +1 | B86: 48.8 | C86: - | D86: 52.3 | E86: - | F86: - | G86: -
A87: Sub-Lease Income +2 | B87: 41.6 | C87: - | D87: 45.1 | E87: - | F87: - | G87: -
A88: Sub-Lease Income +3 | B88: 33.3 | C88: - | D88: 33.4 | E88: - | F88: - | G88: -
A89: Sub-Lease Income +4 | B89: 21.3 | C89: - | D89: 23.6 | E89: - | F89: - | G89: -
A90: Sub-Lease Income +5 | B90: 11.8 | C90: - | D90: 13.1 | E90: - | F90: - | G90: -
A91: Sub-Lease Income, Next 5 Yrs | B91: 156.8 | C91: - | D91: 167.5 | E91: - | F91: - | G91: -
A92: Sub-Lease Income, After 5 Yrs | B92: 57.5 | C92: - | D92: 57 | E92: - | F92: - | G92: -
A94: Interest Rate Data
A95: Filing Date | B95: 46004 | C95: - | D95: 46004 | E95: - | F95: 46049 | G95: -

Sheet Raw - Capital Structure Details
A5: Metro Inc. (TSX:MRU) > Financials > Capital Structure Details
A7: Principal Due in Millions of the reported currency. | B7: Period Type: | C7: Latest | E7: Source:
B8: Currency: | C8: Reported Currency | E8: Conversion: | F8: Historical
B9: Units: | C9: S&P Capital IQ (Default) | E9: Decimals: | F9: Capital IQ (Default)
A12: FQ1 2026 (Dec-20-2025) Capital Structure As Reported Details
A13: Description | B13: Type | C13: Principal Due (CAD) | D13: Coupon/Base Rate | E13: Floating Rate | F13: Maturity | G13: Seniority | H13: Secured | I13: Convertible | J13: Repayment Currency
A14: Lease Liabilities | B14: Capital Lease | C14: 1675.6 | D14: 3.330% | E14: NA | F14: - | G14: Senior | H14: Yes | I14: No | J14: CAD
A15: Loans | B15: Term Loans | C15: 37.8 | D15: 3.570% | E15: NA | F15: 2060 | G15: Senior | H15: No | I15: No | J15: CAD
A16: Revolving Credit Facility | B16: Revolving Credit | C16: 353.8 | D16: 5.750% | E16: Bankers Acceptance Rate | F16: 47828 | G16: Senior | H16: No | I16: No | J16: CAD
A17: Series B Notes | B17: Bonds and Notes | C17: 400 | D17: 5.970% | E17: NA | F17: 49597 | G17: Senior | H17: No | I17: No | J17: CAD
A18: Series D Notes | B18: Bonds and Notes | C18: 300 | D18: 5.030% | E18: NA | F18: 52932 | G18: Senior | H18: No | I18: No | J18: CAD
A19: Series G Notes | B19: Bonds and Notes | C19: 450 | D19: 3.390% | E19: NA | F19: 46727 | G19: Senior | H19: No | I19: No | J19: CAD
A20: Series H Notes | B20: Bonds and Notes | C20: 450 | D20: 4.270% | E20: NA | F20: 54030 | G20: Senior | H20: No | I20: No | J20: CAD
A21: Series I Notes | B21: Bonds and Notes | C21: 400 | D21: 3.410% | E21: NA | F21: 54847 | G21: Senior | H21: No | I21: No | J21: CAD
A22: Series K Notes | B22: Bonds and Notes | C22: 300 | D22: 4.660% | E22: NA | F22: 48617 | G22: Senior | H22: No | I22: No | J22: CAD
A23: Series L Notes | B23: Bonds and Notes | C23: 500 | D23: 3.998% | E23: NA | F23: 47449 | G23: Senior | H23: No | I23: No | J23: CAD
A28: FY 2025 (Sep-27-2025) Capital Structure As Reported Details
A29: Description | B29: Type | C29: Principal Due (CAD) | D29: Coupon/Base Rate | E29: Floating Rate | F29: Maturity | G29: Seniority | H29: Secured | I29: Convertible | J29: Repayment Currency
A30: Lease Liabilities | B30: Capital Lease | C30: 1646.7 | D30: 3.330% | E30: NA | F30: - | G30: Senior | H30: Yes | I30: No | J30: CAD
A31: Loans | B31: Term Loans | C31: 49.9 | D31: 3.570% | E31: NA | F31: 2060 | G31: Senior | H31: No | I31: No | J31: CAD
A32: Revolving Credit Facility | B32: Revolving Credit | C32: 118 | D32: 5.750% | E32: Bankers Acceptance Rate | F32: 47828 | G32: Senior | H32: No | I32: No | J32: CAD
A33: Series B Notes | B33: Bonds and Notes | C33: 400 | D33: 5.970% | E33: NA | F33: 49597 | G33: Senior | H33: No | I33: No | J33: CAD
A34: Series D Notes | B34: Bonds and Notes | C34: 300 | D34: 5.030% | E34: NA | F34: 52932 | G34: Senior | H34: No | I34: No | J34: CAD
A35: Series G Notes | B35: Bonds and Notes | C35: 450 | D35: 3.390% | E35: NA | F35: 46727 | G35: Senior | H35: No | I35: No | J35: CAD
A36: Series H Notes | B36: Bonds and Notes | C36: 450 | D36: 4.270% | E36: NA | F36: 54030 | G36: Senior | H36: No | I36: No | J36: CAD
A37: Series I Notes | B37: Bonds and Notes | C37: 400 | D37: 3.410% | E37: NA | F37: 54847 | G37: Senior | H37: No | I37: No | J37: CAD
A38: Series J Notes | B38: Bonds and Notes | C38: - | D38: 1.920% | E38: NA | F38: 45628 | G38: Senior | H38: No | I38: No | J38: CAD
A39: Series K Notes | B39: Bonds and Notes | C39: 300 | D39: 4.660% | E39: NA | F39: 48617 | G39: Senior | H39: No | I39: No | J39: CAD
A40: Series L Notes | B40: Bonds and Notes | C40: 500 | D40: 3.998% | E40: NA | F40: 47449 | G40: Senior | H40: No | I40: No | J40: CAD

Sheet Raw - Multiples
A5: Metro Inc. (TSX:MRU) > Financials > Multiples
B7: View: | C7: Data | E7: Frequency: | F7: Quarterly
B8: Order: | C8: Latest on Right | E8: Decimals: | F8: Capital IQ (Default)
B9: Dilution: | C9: Basic
A12: Multiples Detail In Millions of the reported currency, except per share items.
A14: For Quarter Ending | C14: 45565 | D14: 45657 | E14: 45747 | F14: 45838 | G14: 45930 | H14: 46022 | I14: 46087
A15: TEV/LTM Total Revenue | B15: Average | C15: 1.0754722 | D15: 1.1198745 | E15: 1.1687033 | F15: 1.2616849 | G15: 1.2093331 | H15: 1.1502318 | I15: 1.1472532
B16: High | C16: 1.112477 | D16: 1.183329 | E16: 1.240402 | F16: 1.30121 | G16: 1.286345 | H16: 1.187016 | I16: 1.175668
B17: Low | C17: 1.031841 | D17: 1.059061 | E17: 1.124481 | F17: 1.20616 | G17: 1.110907 | H17: 1.103289 | I17: 1.088951
B18: Close | C18: 1.099325 | D18: 1.144688 | E18: 1.240402 | F18: 1.289035 | G18: 1.123472 | H18: 1.166796 | I18: 1.131762
A20: TEV/NTM Total Revenues | B20: Average | C20: 1.063935 | D20: 1.09565 | E20: 1.127615 | F20: 1.216082 | G20: 1.147339 | H20: 1.092871 | I20: 1.112202
B21: High | C21: 1.103129 | D21: 1.141605 | E21: 1.196327 | F21: 1.253985 | G21: 1.239435 | H21: 1.150722 | I21: 1.140709
B22: Low | C22: 1.018144 | D22: 1.049361 | E22: 1.0871 | F22: 1.163217 | G22: 1.030494 | H22: 1.023427 | I22: 1.055173
B23: Close | C23: 1.090088 | D23: 1.105274 | E23: 1.196327 | F23: 1.242252 | G23: 1.04215 | H23: 1.132101 | I23: 1.096656
A25: TEV/LTM EBITDA | B25: Average | C25: 11.77606 | D25: 12.184655 | E25: 12.689762 | F25: 13.667017 | G25: 13.049602 | H25: 12.366983 | I25: 12.474563
B26: High | C26: 12.212716 | D26: 12.768185 | E26: 13.468777 | F26: 14.08821 | G26: 13.927273 | H26: 12.744831 | I26: 12.796832
B27: Low | C27: 11.265268 | D27: 11.626316 | E27: 12.21006 | F27: 13.096963 | G27: 11.949862 | H27: 11.867912 | I27: 11.866303
B28: Close | C28: 12.068334 | D28: 12.42782 | E28: 13.468777 | F28: 13.956398 | G28: 12.085027 | H28: 12.642707 | I28: 12.332813
A30: TEV/NTM EBITDA | B30: Average | C30: 11.085896 | D30: 11.390905 | E30: 11.746854 | F30: 12.667247 | G30: 12.108841 | H30: 11.556071 | I30: 11.498479
B31: High | C31: 11.432173 | D31: 11.897186 | E31: 12.457651 | F31: 13.063514 | G31: 12.906488 | H31: 11.945377 | I31: 11.826493
B32: Low | C32: 10.682653 | D32: 10.88325 | E32: 11.298054 | F32: 12.11269 | G32: 11.127761 | H32: 11.051444 | I32: 10.890245
B33: Close | C33: 11.29702 | D33: 11.520721 | E33: 12.457651 | F33: 12.941285 | G33: 11.253624 | H33: 11.737249 | I33: 11.318389
A35: TEV/LTM EBIT | B35: Average | C35: 16.154278 | D35: 16.884218 | E35: 17.506372 | F35: 18.835173 | G35: 17.992206 | H35: 17.157883 | I35: 17.284698
B36: High | C36: 16.818858 | D36: 17.811138 | E36: 18.577168 | F36: 19.412368 | G36: 19.190609 | H36: 17.844331 | I36: 17.772165
B37: Low | C37: 15.38471 | D37: 16.011291 | E37: 16.841049 | F37: 18.064333 | G37: 16.485369 | H37: 16.372315 | I37: 16.479852
B38: Close | C38: 16.62002 | D38: 17.154078 | E38: 18.577168 | F38: 19.230742 | G38: 16.671834 | H38: 17.452143 | I38: 17.127738
A40: TEV/NTM EBIT | B40: Average | C40: 15.286972 | D40: 15.674797 | E40: 16.006881 | F40: 17.283879 | G40: 16.582285 | H40: 15.897917 | I40: 15.805726
B41: High | C41: 15.880095 | D41: 16.327562 | E41: 16.95055 | F41: 17.838936 | G41: 17.615484 | H41: 16.435921 | I41: 16.281429
B42: Low | C42: 14.572827 | D42: 14.94052 | E42: 15.283462 | F42: 16.450694 | G42: 15.248059 | H42: 15.143484 | I42: 14.960759
B43: Close | C43: 15.692359 | D43: 15.808524 | E43: 16.95055 | F43: 17.672025 | G43: 15.420526 | H43: 16.158568 | I43: 15.548933
A45: P/LTM EPS | B45: Average | C45: 19.763128 | D45: 21.37763 | E45: 21.963786 | F45: 23.497451 | G45: 22.219831 | H45: 20.956379 | I45: 21.201652
B46: High | C46: 21.227178 | D46: 22.781021 | E46: 23.381403 | F46: 24.287182 | G46: 24.084714 | H46: 21.773218 | I46: 22.019436
B47: Low | C47: 18.018354 | D47: 19.993921 | E47: 20.692086 | F47: 22.605684 | G47: 20.012115 | H47: 19.844986 | I47: 19.99133
B48: Close | C48: 20.918863 | D48: 21.934306 | E48: 23.381403 | F48: 24.064467 | G48: 20.28777 | H48: 21.336933 | I48: 21.037452
A50: P/NTM EPS | B50: Average | C50: 18.188399 | D50: 18.795105 | E50: 19.100359 | F50: 20.697545 | G50: 19.776076 | H50: 18.797396 | I50: 18.449913
B51: High | C51: 18.883736 | D51: 19.765161 | E51: 20.345226 | F51: 21.449154 | G51: 21.269502 | H51: 19.478475 | I51: 19.225068
B52: Low | C52: 17.231288 | D52: 17.786626 | E52: 18.280528 | F52: 19.661834 | G52: 17.990603 | H52: 17.840348 | I52: 17.153749
B53: Close | C53: 18.609464 | D53: 19.046423 | E53: 20.345226 | F53: 21.252457 | G53: 18.238409 | H53: 19.001956 | I53: 18.051394
A55: P/LTM Normalized EPS | B55: Average | C55: 23.795969 | D55: 25.211016 | E55: 26.320713 | F55: 28.675955 | G55: 27.327359 | H55: 25.910304 | I55: 25.84493
B56: High | C56: 25.04002 | D56: 26.858062 | E56: 28.20552 | F56: 29.710795 | G56: 29.463114 | H56: 26.925568 | I56: 26.695868
B57: Low | C57: 22.230653 | D57: 23.585246 | E57: 24.961336 | F57: 27.269752 | G57: 24.738461 | H57: 24.53186 | I57: 24.154124
B58: Close | C58: 24.676327 | D58: 25.859813 | E58: 28.20552 | F58: 29.438345 | G58: 25.079219 | H58: 26.386041 | I58: 25.41808
A60: P/BV | B60: Average | C60: 2.6969826 | D60: 2.8129856 | E60: 2.9056815 | F60: 3.2212972 | G60: 3.0940852 | H60: 2.95468 | I60: 2.9445025
B61: High | C61: 2.818852 | D61: 2.965752 | E61: 3.11344 | F61: 3.349435 | G61: 3.321512 | H61: 3.080926 | I61: 3.054643
B62: Low | C62: 2.539319 | D62: 2.655083 | E62: 2.755334 | F62: 3.010146 | G62: 2.812479 | H62: 2.788991 | I62: 2.744403
B63: Close | C63: 2.77791 | D63: 2.855522 | E63: 3.11344 | F63: 3.31872 | G63: 2.851219 | H63: 3.019191 | I63: 2.888014
A65: P/Tangible BV | B65: Average | C65: 22.137905 | D65: 21.547698 | E65: 19.095934 | F65: 21.076153 | G65: 19.755156 | H65: 19.038391 | I65: 19.674699
B66: High | C66: 23.258675 | D66: 23.508019 | E66: 20.309668 | F66: 22.000048 | G66: 21.816646 | H66: 20.649319 | I66: 20.473162
B67: Low | C67: 20.719438 | D67: 19.20267 | E67: 17.677267 | F67: 19.312055 | G67: 17.469416 | H67: 17.323522 | I67: 18.302279
B68: Close | C68: 22.920855 | D68: 19.879659 | E68: 19.974753 | F68: 21.798306 | G68: 17.710047 | H68: 20.235555 | I68: 19.260016
A70: TEV/LTM Unlevered FCF | B70: Average | C70: 34.76084 | D70: 31.750173 | E70: 28.553623 | F70: 33.182495 | G70: 30.237007 | H70: 27.122101 | I70: 26.83597
B71: High | C71: 36.082394 | D71: 35.448561 | E71: 30.48254 | F71: 34.682681 | G71: 34.286481 | H71: 28.414283 | I71: 27.501542
B72: Low | C72: 33.661819 | D72: 27.555501 | E72: 27.201425 | F72: 29.64105 | G72: 26.06204 | H72: 25.883311 | I72: 25.501751
B73: Close | C73: 34.7533 | D73: 27.555501 | E73: 30.48254 | F73: 34.358182 | G73: 26.356826 | H73: 27.242053 | I73: 26.504323
A75: Market Cap/LTM Levered FCF | B75: Average | C75: 33.255289 | D75: 30.082144 | E75: 26.642394 | F75: 31.697892 | G75: 28.549195 | H75: 24.981937 | I75: 24.524668
B76: High | C76: 34.579773 | D76: 34.292317 | E76: 28.75333 | F76: 33.382988 | G76: 32.929767 | H76: 26.003847 | I76: 25.36336
B77: Low | C77: 32.17261 | D77: 25.268875 | E77: 25.294864 | F77: 27.799387 | G77: 24.012441 | H77: 23.811904 | I77: 22.931272
B78: Close | C78: 33.467491 | D78: 25.696065 | E78: 28.75333 | F78: 33.011788 | G78: 24.343198 | H78: 25.131073 | I78: 24.06039
A80: Average multiples are calculated using positive close values on each trading day within the frequency periods selected. Negative values are excluded from the calculation. When the Multiples are not meaningful, due to negative values, then they will not be displayed in the chart.
A82: When a mismatch exists between the currency of the equity listing and the reported financial results such results are translated into the currency of the listing at the exchange rate applicable on the financial period end date.
A86: Historical Equity Pricing Data supplied by Interactive Data Pricing and Reference Data LLC
